Workbook

Sheet Data Export
A1: Participant Key | B1: Group | C1: Task_1_G1 | D1: Task_1_G2 | E1: Task_1_G3 | F1: Task_1_G4 | G1: Task_1_G5 | H1: Task_1_G6 | I1: Task_1_G7 | J1: Task_1_G8 | K1: Task_1_G9 | L1: Task_1_G10 | M1: Task_1_G11 | N1: Task_1_G12 | O1: Task_1_G13 | P1: Task_1_G14 | Q1: Task_2 | R1: Task_3 | S1: Task_1_P_Unscaled | T1: Task_1_P_Scaled | U1: Task_1_Perf | V1: Task_1_p | W1: Task_1_A1 | X1: Task_1_A2 | Y1: Task_1_A3 | Z1: Task_1_A4 | AA1: Task_1_A5 | AB1: Task_1_A6 | AC1: Task_1_A7 | AD1: Task_1_A8 | AE1: Task_1_A9 | AF1: Task_1_A10 | AG1: Task_1_A11 | AH1: Task_1_A12 | AI1: Task_1_A13 | AJ1: Task_1_A14 | AK1: Task_2_A | AL1: Task_3_A | AM1: Task_1_M1 | AN1: Task_1_M2 | AO1: Task_1_M3 | AP1: Task_1_M4 | AQ1: Task_1_M5 | AR1: Task_1_M6 | AS1: Task_1_M7 | AT1: Task_1_M8 | AU1: Task_1_M9 | AV1: Task_1_M10 | AW1: Task_1_M11 | AX1: Task_1_M12 | AY1: Task_1_M13 | AZ1: Task_1_M14 | BA1: Task_2_M | BB1: Task_3_M | BC1: Max_Unscaled | BD1: Max_Scaled
A2: ='Task 1'!A48 -> fe6c | B2: =VLOOKUP(A2,'Task 1'!A$48:B$59,2,FALSE) -> B | C2: =VLOOKUP($A2,'Task 1'!$A$16:$P$27,'Task 1'!C$14,FALSE) -> 3 | D2: =VLOOKUP($A2,'Task 1'!$A$16:$P$27,'Task 1'!D$14,FALSE) -> 1 | E2: =VLOOKUP($A2,'Task 1'!$A$16:$P$27,'Task 1'!E$14,FALSE) -> 1 | F2: =VLOOKUP($A2,'Task 1'!$A$16:$P$27,'Task 1'!F$14,FALSE) -> 1 | G2: =VLOOKUP($A2,'Task 1'!$A$16:$P$27,'Task 1'!G$14,FALSE) -> 0 | H2: =VLOOKUP($A2,'Task 1'!$A$16:$P$27,'Task 1'!H$14,FALSE) -> 1 | I2: =VLOOKUP($A2,'Task 1'!$A$16:$P$27,'Task 1'!I$14,FALSE) -> 1 | J2: =VLOOKUP($A2,'Task 1'!$A$16:$P$27,'Task 1'!J$14,FALSE) -> 1 | ... P2: =VLOOKUP($A2,'Task 1'!$A$16:$P$27,'Task 1'!P$14,FALSE) -> 0 | Q2: =VLOOKUP($A2,'Task 2'!$A$2:$J$12,10,FALSE) -> 0 | R2: =VLOOKUP($A2,'Task 3'!$A$2:$J$12,10,FALSE) -> 0 | S2: =VLOOKUP($A2,'Task 1'!$A$16:$V$27,17,FALSE) -> 13 | T2: =VLOOKUP($A2,'Task 1'!$A$16:$V$27,18,FALSE) -> 51 | U2: =VLOOKUP($A2,'Task 1'!$A$16:$V$27,19,FALSE) -> 0.60714286 | V2: =VLOOKUP($A2,'Task 1'!$A$16:$W$27,23,FALSE) -> 0.58333333 | W2: =IF(VLOOKUP($A2,'Task 1'!$A$2:$P$13,'Task 1'!C$14,FALSE)="","",VLOOKUP($A2,'Task 1'!$A$2:$P$13,'Task 1'!C$14,FALSE)) -> The goal is to enhance the `finance_tracker` project by adding income tracking functionality to complement the existing expense, budget, user, and reporting features. | X2: =IF(VLOOKUP($A2,'Task 1'!$A$2:$P$13,'Task 1'!D$14,FALSE)="","",VLOOKUP($A2,'Task 1'!$A$2:$P$13,'Task 1'!D$14,FALSE)) -> No, the task was not completed. | Y2: =IF(VLOOKUP($A2,'Task 1'!$A$2:$P$13,'Task 1'!E$14,FALSE)="","",VLOOKUP($A2,'Task 1'!$A$2:$P$13,'Task 1'!E$14,FALSE)) -> Gather relevant information', 'summarize requirements', 'code implementation and show the diff', 'run tests and solve runtime errors' | Z2: =IF(VLOOKUP($A2,'Task 1'!$A$2:$P$13,'Task 1'!F$14,FALSE)="","",VLOOKUP($A2,'Task 1'!$A$2:$P$13,'Task 1'!F$14,FALSE)) -> run tests and modify the code to solve errors. | AA2: =IF(VLOOKUP($A2,'Task 1'!$A$2:$P$13,'Task 1'!G$14,FALSE)="","",VLOOKUP($A2,'Task 1'!$A$2:$P$13,'Task 1'!G$14,FALSE)) | AB2: =IF(VLOOKUP($A2,'Task 1'!$A$2:$P$13,'Task 1'!H$14,FALSE)="","",VLOOKUP($A2,'Task 1'!$A$2:$P$13,'Task 1'!H$14,FALSE)) -> Yes, maybe the step where it try to solve the same runtime errors again and again. | AC2: =IF(VLOOKUP($A2,'Task 1'!$A$2:$P$13,'Task 1'!I$14,FALSE)="","",VLOOKUP($A2,'Task 1'!$A$2:$P$13,'Task 1'!I$14,FALSE)) -> --old_str 'from finance_tracker.reports import FinancialReport' --new_str 'from finance_tracker.reports import FinancialReport from finance_tracker.income import IncomeTracker' | AD2: =IF(VLOOKUP($A2,'Task 1'!$A$2:$P$13,'Task 1'!J$14,FALSE)="","",VLOOKUP($A2,'Task 1'!$A$2:$P$13,'Task 1'!J$14,FALSE)) -> finance_tracker/cli.py, finance_tracker/reports.py | ... AJ2: =IF(VLOOKUP($A2,'Task 1'!$A$2:$P$13,'Task 1'!P$14,FALSE)="","",VLOOKUP($A2,'Task 1'!$A$2:$P$13,'Task 1'!P$14,FALSE)) | AK2: =IF(VLOOKUP($A2,Form_Responses8[[Participant Key]:[Find and describe all potential bugs!]],3,FALSE)="","",VLOOKUP($A2,Form_Responses8[[Participant Key]:[Find and describe all potential bugs!]],3,FALSE)) -> Agent's logic: failed to change to another method to fix the issue. Implementation: the line break conditional statements seems was incorrect at some point. | AL2: =IF(VLOOKUP($A2,Form_Responses6[[Participant Key]:[Find and describe all potential bugs!]],3,FALSE)="","",VLOOKUP($A2,Form_Responses6[[Participant Key]:[Find and describe all potential bugs!]],3,FALSE)) -> Agent's decision making: the failed command outputs mention that more commands could be run in a docker container, but the agent fails to adjust the next steps to adapt it. Logic: allows the failed steps repeat multiple times. | AM2: {=INDEX('Task 1'!$B$30:$B$43,COLUMN(A1))} -> 3 | AN2: {=INDEX('Task 1'!$B$30:$B$43,COLUMN(B1))} -> 1 | AO2: {=INDEX('Task 1'!$B$30:$B$43,COLUMN(C1))} -> 2 | AP2: {=INDEX('Task 1'!$B$30:$B$43,COLUMN(D1))} -> 1 | AQ2: {=INDEX('Task 1'!$B$30:$B$43,COLUMN(E1))} -> 1 | AR2: {=INDEX('Task 1'!$B$30:$B$43,COLUMN(F1))} -> 2 | AS2: {=INDEX('Task 1'!$B$30:$B$43,COLUMN(G1))} -> 1 | AT2: {=INDEX('Task 1'!$B$30:$B$43,COLUMN(H1))} -> 2 | ... AZ2: {=INDEX('Task 1'!$B$30:$B$43,COLUMN(N1))} -> 2 | BA2: 1 | BB2: 1 | BC2: ='Task 1'!$B$45 -> 21 | BD2: ='Task 1'!$D$45 -> 84
A3: ='Task 1'!A49 -> 67c3 | B3: =VLOOKUP(A3,'Task 1'!A$48:B$59,2,FALSE) -> B | C3: =VLOOKUP($A3,'Task 1'!$A$16:$P$27,'Task 1'!C$14,FALSE) -> 0 | D3: =VLOOKUP($A3,'Task 1'!$A$16:$P$27,'Task 1'!D$14,FALSE) -> 1 | E3: =VLOOKUP($A3,'Task 1'!$A$16:$P$27,'Task 1'!E$14,FALSE) -> 0 | F3: =VLOOKUP($A3,'Task 1'!$A$16:$P$27,'Task 1'!F$14,FALSE) -> 0 | G3: =VLOOKUP($A3,'Task 1'!$A$16:$P$27,'Task 1'!G$14,FALSE) -> 0 | H3: =VLOOKUP($A3,'Task 1'!$A$16:$P$27,'Task 1'!H$14,FALSE) -> 0 | I3: =VLOOKUP($A3,'Task 1'!$A$16:$P$27,'Task 1'!I$14,FALSE) -> 0 | J3: =VLOOKUP($A3,'Task 1'!$A$16:$P$27,'Task 1'!J$14,FALSE) -> 0 | ... P3: =VLOOKUP($A3,'Task 1'!$A$16:$P$27,'Task 1'!P$14,FALSE) -> 0 | Q3: =VLOOKUP($A3,'Task 2'!$A$2:$J$12,10,FALSE) -> 0 | R3: =VLOOKUP($A3,'Task 3'!$A$2:$J$12,10,FALSE) -> 0 | S3: =VLOOKUP($A3,'Task 1'!$A$16:$V$27,17,FALSE) -> 2 | T3: =VLOOKUP($A3,'Task 1'!$A$16:$V$27,18,FALSE) -> 12 | U3: =VLOOKUP($A3,'Task 1'!$A$16:$V$27,19,FALSE) -> 0.14285714 | V3: =VLOOKUP($A3,'Task 1'!$A$16:$W$27,23,FALSE) -> 0.91666667 | W3: =IF(VLOOKUP($A3,'Task 1'!$A$2:$P$13,'Task 1'!C$14,FALSE)="","",VLOOKUP($A3,'Task 1'!$A$2:$P$13,'Task 1'!C$14,FALSE)) | X3: =IF(VLOOKUP($A3,'Task 1'!$A$2:$P$13,'Task 1'!D$14,FALSE)="","",VLOOKUP($A3,'Task 1'!$A$2:$P$13,'Task 1'!D$14,FALSE)) -> No, the task was not completed. | Y3: =IF(VLOOKUP($A3,'Task 1'!$A$2:$P$13,'Task 1'!E$14,FALSE)="","",VLOOKUP($A3,'Task 1'!$A$2:$P$13,'Task 1'!E$14,FALSE)) -> Execute solutions and take over corrections | Z3: =IF(VLOOKUP($A3,'Task 1'!$A$2:$P$13,'Task 1'!F$14,FALSE)="","",VLOOKUP($A3,'Task 1'!$A$2:$P$13,'Task 1'!F$14,FALSE)) -> Ask and add error fixes | AA3: =IF(VLOOKUP($A3,'Task 1'!$A$2:$P$13,'Task 1'!G$14,FALSE)="","",VLOOKUP($A3,'Task 1'!$A$2:$P$13,'Task 1'!G$14,FALSE)) -> Missing libraries, non-working feature | AB3: =IF(VLOOKUP($A3,'Task 1'!$A$2:$P$13,'Task 1'!H$14,FALSE)="","",VLOOKUP($A3,'Task 1'!$A$2:$P$13,'Task 1'!H$14,FALSE)) | AC3: =IF(VLOOKUP($A3,'Task 1'!$A$2:$P$13,'Task 1'!I$14,FALSE)="","",VLOOKUP($A3,'Task 1'!$A$2:$P$13,'Task 1'!I$14,FALSE)) | AD3: =IF(VLOOKUP($A3,'Task 1'!$A$2:$P$13,'Task 1'!J$14,FALSE)="","",VLOOKUP($A3,'Task 1'!$A$2:$P$13,'Task 1'!J$14,FALSE)) | ... AJ3: =IF(VLOOKUP($A3,'Task 1'!$A$2:$P$13,'Task 1'!P$14,FALSE)="","",VLOOKUP($A3,'Task 1'!$A$2:$P$13,'Task 1'!P$14,FALSE)) | AK3: =IF(VLOOKUP($A3,Form_Responses8[[Participant Key]:[Find and describe all potential bugs!]],3,FALSE)="","",VLOOKUP($A3,Form_Responses8[[Participant Key]:[Find and describe all potential bugs!]],3,FALSE)) | AL3: =IF(VLOOKUP($A3,Form_Responses6[[Participant Key]:[Find and describe all potential bugs!]],3,FALSE)="","",VLOOKUP($A3,Form_Responses6[[Participant Key]:[Find and describe all potential bugs!]],3,FALSE)) -> No access to the environment and therefore can’t install or update anything, missing tools that are supposed to be used | AM3: {=INDEX('Task 1'!$B$30:$B$43,COLUMN(A2))} -> 3 | AN3: {=INDEX('Task 1'!$B$30:$B$43,COLUMN(B2))} -> 1 | AO3: {=INDEX('Task 1'!$B$30:$B$43,COLUMN(C2))} -> 2 | AP3: {=INDEX('Task 1'!$B$30:$B$43,COLUMN(D2))} -> 1 | AQ3: {=INDEX('Task 1'!$B$30:$B$43,COLUMN(E2))} -> 1 | AR3: {=INDEX('Task 1'!$B$30:$B$43,COLUMN(F2))} -> 2 | AS3: {=INDEX('Task 1'!$B$30:$B$43,COLUMN(G2))} -> 1 | AT3: {=INDEX('Task 1'!$B$30:$B$43,COLUMN(H2))} -> 2 | ... AZ3: {=INDEX('Task 1'!$B$30:$B$43,COLUMN(N2))} -> 2 | BA3: 1 | BB3: 1 | BC3: ='Task 1'!$B$45 -> 21 | BD3: ='Task 1'!$D$45 -> 84
A4: ='Task 1'!A50 -> 0078 | B4: =VLOOKUP(A4,'Task 1'!A$48:B$59,2,FALSE) -> A | C4: =VLOOKUP($A4,'Task 1'!$A$16:$P$27,'Task 1'!C$14,FALSE) -> 2 | D4: =VLOOKUP($A4,'Task 1'!$A$16:$P$27,'Task 1'!D$14,FALSE) -> 0 | E4: =VLOOKUP($A4,'Task 1'!$A$16:$P$27,'Task 1'!E$14,FALSE) -> 0 | F4: =VLOOKUP($A4,'Task 1'!$A$16:$P$27,'Task 1'!F$14,FALSE) -> 1 | G4: =VLOOKUP($A4,'Task 1'!$A$16:$P$27,'Task 1'!G$14,FALSE) -> 1 | H4: =VLOOKUP($A4,'Task 1'!$A$16:$P$27,'Task 1'!H$14,FALSE) -> 1 | I4: =VLOOKUP($A4,'Task 1'!$A$16:$P$27,'Task 1'!I$14,FALSE) -> 1 | J4: =VLOOKUP($A4,'Task 1'!$A$16:$P$27,'Task 1'!J$14,FALSE) -> 2 | ... P4: =VLOOKUP($A4,'Task 1'!$A$16:$P$27,'Task 1'!P$14,FALSE) -> 0 | Q4: =VLOOKUP($A4,'Task 2'!$A$2:$J$12,10,FALSE) -> 0 | R4: =VLOOKUP($A4,'Task 3'!$A$2:$J$12,10,FALSE) -> 1 | S4: =VLOOKUP($A4,'Task 1'!$A$16:$V$27,17,FALSE) -> 13 | T4: =VLOOKUP($A4,'Task 1'!$A$16:$V$27,18,FALSE) -> 55 | U4: =VLOOKUP($A4,'Task 1'!$A$16:$V$27,19,FALSE) -> 0.6547619 | V4: =VLOOKUP($A4,'Task 1'!$A$16:$W$27,23,FALSE) -> 0.5 | W4: =IF(VLOOKUP($A4,'Task 1'!$A$2:$P$13,'Task 1'!C$14,FALSE)="","",VLOOKUP($A4,'Task 1'!$A$2:$P$13,'Task 1'!C$14,FALSE)) -> The agents goal is to implement an income tracking feature to a python project with cli functionality and integrating it into the rest of the program. | X4: =IF(VLOOKUP($A4,'Task 1'!$A$2:$P$13,'Task 1'!D$14,FALSE)="","",VLOOKUP($A4,'Task 1'!$A$2:$P$13,'Task 1'!D$14,FALSE)) -> Yes, the task was completed successfully. | Y4: =IF(VLOOKUP($A4,'Task 1'!$A$2:$P$13,'Task 1'!E$14,FALSE)="","",VLOOKUP($A4,'Task 1'!$A$2:$P$13,'Task 1'!E$14,FALSE)) -> Adding functionality of income tracking and integrating it into the CLI | Z4: =IF(VLOOKUP($A4,'Task 1'!$A$2:$P$13,'Task 1'!F$14,FALSE)="","",VLOOKUP($A4,'Task 1'!$A$2:$P$13,'Task 1'!F$14,FALSE)) -> adding the income report generation to the cli | AA4: =IF(VLOOKUP($A4,'Task 1'!$A$2:$P$13,'Task 1'!G$14,FALSE)="","",VLOOKUP($A4,'Task 1'!$A$2:$P$13,'Task 1'!G$14,FALSE)) -> The agent seems to have troubles with python syntax, i.e., the indentation (IndentationError) | AB4: =IF(VLOOKUP($A4,'Task 1'!$A$2:$P$13,'Task 1'!H$14,FALSE)="","",VLOOKUP($A4,'Task 1'!$A$2:$P$13,'Task 1'!H$14,FALSE)) -> Yes, it does. It requests multiple times to “Create the 'IncomeTracker' class ... to satisfy the PR description", the commit titles also indicate this with multiple "Add income report generation to CLI" | AC4: =IF(VLOOKUP($A4,'Task 1'!$A$2:$P$13,'Task 1'!I$14,FALSE)="","",VLOOKUP($A4,'Task 1'!$A$2:$P$13,'Task 1'!I$14,FALSE)) -> import cmd 2 import argparse 3 from finance_tracker.expenses import ExpenseTracker 4 from finance_tracker.budgets import BudgetManager 5 from finance_tracker.users import UserManager 6 from finance_tracker.reports import FinancialReport 7 from finance_tracker.income import IncomeTracker 8 from datetime import datetime 9 10 class FinanceTrackerCLI(cmd.Cmd): 11 """Command-line interface for the finance tracker.""" 12 prompt = "FinanceTracker> " 13 intro = "Welcome to the Personal Finance Tracker. Type 'help' for commands." 14 15 def __init__(self): 16 super().__init__() 17 self.user_manager = UserManager() 18 self.current_user = None 19 self.expense_tracker = None 20 self.budget_manager = None 21 self.report_generator = None 22 23 def do_login(self, arg): 24 """Login to the system: login <username> <password>""" 25 args = arg.split() 26 if len(args) != 2: 27 print("Usage: login <username> <password>") 28 return 29 username, password = args 30 if self.user_manager.authenticate_user(username, password): 31 self.current_user = username 32 self.expense_tracker = ExpenseTracker(username) 33 self.budget_manager = BudgetManager(username) 34 self.report_generator = FinancialReport(username, self.expense_tracker, self.budget_manager) 35 print(f"Logged in as {username}") 36 else: 37 print("Invalid username or password") 38 39 def do_register(self, arg): 40 """Register a new user: register <username> <password> <email>""" 41 args = arg.split() 42 if len(args) != 3: 43 print("Usage: register <username> <password> <email>") 44 return 45 try: 46 self.user_manager.register_user(*args) 47 print(f"User {args[0]} registered successfully") 48 except ValueError as e: 49 print(f"Error: {e}") 50 51 def do_add_expense(self, arg): 52 """Add an expense: add_expense <amount> <category> <description> [tags] [recurring] [period]""" 53 if not self.current_user: 54 print("Please login first") 55 return 56 args = arg.split() 57 if len(args) < 3: 58 print("Usage: add_expense <amount> <category> <description> [tags] [recurring] [period]") 59 return 60 amount, category, description = args[:3] 61 tags = args[3].split(",") if len(args) > 3 else [] 62 is_recurring = args[4].lower() == "true" if len(args) > 4 else False 63 period = args[5] if len(args) > 5 else None 64 try: 65 expense_id = self.expense_tracker.add_expense(float(amount), category, description, 66 tags=tags, is_recurring=is_recurring, 67 recurrence_period=period) 68 print(f"Expense added with ID: {expense_id}") 69 except ValueError as e: 70 print(f"Error: {e}") 71 72 def do_set_budget(self, arg): 73 """Set a budget: set_budget <category> <amount> [period] [alert_threshold]""" 74 if not self.current_user: 75 print("Please login first") 76 return 77 args = arg.split() 78 if len(args) < 2: 79 print("Usage: set_budget <category> <amount> [period] [alert_threshold]") 80 return 81 category, amount = args[:2] 82 period = args[2] if len(args) > 2 else "monthly" 83 alert_threshold = float(args[3]) if len(args) > 3 else 0.8 84 try: 85 self.budget_manager.set_budget(category, float(amount), period, alert_threshold) 86 print(f"Budget set for {category} ({period})") 87 except ValueError as e: 88 print(f"Error: {e}") 89 90 def do_generate_report(self, arg): 91 """Generate a report: generate_report <type> [start_date] [end_date]""" 92 if not self.current_user: 93 print("Please login first") 94 return 95 args = arg.split() 96 if len(args) < 1: 97 print("Usage: generate_report <type> [start_date] [end_date]") 98 return 99 report_type = args[0] 100 start_date = args[1] if len(args) > 1 else None 101 end_date = args[2] if len(args) > 2 else None 102 try: 103 report_file = self.report_generator.generate_report_pdf(report_type, start_date, end_date) 104 print(f"Report generated: {report_file}") 105 except Exception as e: 106 print(f"Error: {e}") 107 108 def do_exit(self, arg): 109 """Exit the CLI.""" 110 print("Goodbye!") 111 return True 112 113 def preloop(self): 114 """Initialize CLI state.""" 115 print("Personal Finance Tracker CLI. Type 'register' or 'login' to begin.") | AD4: =IF(VLOOKUP($A4,'Task 1'!$A$2:$P$13,'Task 1'!J$14,FALSE)="","",VLOOKUP($A4,'Task 1'!$A$2:$P$13,'Task 1'!J$14,FALSE)) -> cli.py, report.py, income.py | ... AJ4: =IF(VLOOKUP($A4,'Task 1'!$A$2:$P$13,'Task 1'!P$14,FALSE)="","",VLOOKUP($A4,'Task 1'!$A$2:$P$13,'Task 1'!P$14,FALSE)) -> first test, then error so next "updated logic" | AK4: =IF(VLOOKUP($A4,Form_Responses8[[Participant Key]:[Find and describe all potential bugs!]],3,FALSE)="","",VLOOKUP($A4,Form_Responses8[[Participant Key]:[Find and describe all potential bugs!]],3,FALSE)) -> The LLM suggests to update the read method to account for both \r and \n characters, but the agent misinterprets it and removes the \n (which was correct), instead of adding a new if-case for \r. | AL4: =IF(VLOOKUP($A4,Form_Responses6[[Participant Key]:[Find and describe all potential bugs!]],3,FALSE)="","",VLOOKUP($A4,Form_Responses6[[Participant Key]:[Find and describe all potential bugs!]],3,FALSE)) -> The agent tries to use forbidden commands (for which it has no permission) multiple times. It also tries to chain commands, which also does not seem to work. The LLM suggests to write a dockerfile, but the agent runs into problems. The agent and LLM do not seem to recognize that they are running in circles. It seems like after "The agent acknowledges that the LLM's training data is current only until October 2023.", the agent loses its "history" and tries commands again which have not worked before. | AM4: {=INDEX('Task 1'!$B$30:$B$43,COLUMN(A3))} -> 3 | AN4: {=INDEX('Task 1'!$B$30:$B$43,COLUMN(B3))} -> 1 | AO4: {=INDEX('Task 1'!$B$30:$B$43,COLUMN(C3))} -> 2 | AP4: {=INDEX('Task 1'!$B$30:$B$43,COLUMN(D3))} -> 1 | AQ4: {=INDEX('Task 1'!$B$30:$B$43,COLUMN(E3))} -> 1 | AR4: {=INDEX('Task 1'!$B$30:$B$43,COLUMN(F3))} -> 2 | AS4: {=INDEX('Task 1'!$B$30:$B$43,COLUMN(G3))} -> 1 | AT4: {=INDEX('Task 1'!$B$30:$B$43,COLUMN(H3))} -> 2 | ... AZ4: {=INDEX('Task 1'!$B$30:$B$43,COLUMN(N3))} -> 2 | BA4: 1 | BB4: 1 | BC4: ='Task 1'!$B$45 -> 21 | BD4: ='Task 1'!$D$45 -> 84
A5: ='Task 1'!A51 -> 1d20 | B5: =VLOOKUP(A5,'Task 1'!A$48:B$59,2,FALSE) -> A | C5: =VLOOKUP($A5,'Task 1'!$A$16:$P$27,'Task 1'!C$14,FALSE) -> 1 | D5: =VLOOKUP($A5,'Task 1'!$A$16:$P$27,'Task 1'!D$14,FALSE) -> 1 | E5: =VLOOKUP($A5,'Task 1'!$A$16:$P$27,'Task 1'!E$14,FALSE) -> 2 | F5: =VLOOKUP($A5,'Task 1'!$A$16:$P$27,'Task 1'!F$14,FALSE) -> 1 | G5: =VLOOKUP($A5,'Task 1'!$A$16:$P$27,'Task 1'!G$14,FALSE) -> 1 | H5: =VLOOKUP($A5,'Task 1'!$A$16:$P$27,'Task 1'!H$14,FALSE) -> 1 | I5: =VLOOKUP($A5,'Task 1'!$A$16:$P$27,'Task 1'!I$14,FALSE) -> 1 | J5: =VLOOKUP($A5,'Task 1'!$A$16:$P$27,'Task 1'!J$14,FALSE) -> 1 | ... P5: =VLOOKUP($A5,'Task 1'!$A$16:$P$27,'Task 1'!P$14,FALSE) -> 1 | Q5: =VLOOKUP($A5,'Task 2'!$A$2:$J$12,10,FALSE) -> 1 | R5: =VLOOKUP($A5,'Task 3'!$A$2:$J$12,10,FALSE) -> 1 | S5: =VLOOKUP($A5,'Task 1'!$A$16:$V$27,17,FALSE) -> 16 | T5: =VLOOKUP($A5,'Task 1'!$A$16:$V$27,18,FALSE) -> 71 | U5: =VLOOKUP($A5,'Task 1'!$A$16:$V$27,19,FALSE) -> 0.8452381 | V5: =VLOOKUP($A5,'Task 1'!$A$16:$W$27,23,FALSE) -> 0.083333333 | W5: =IF(VLOOKUP($A5,'Task 1'!$A$2:$P$13,'Task 1'!C$14,FALSE)="","",VLOOKUP($A5,'Task 1'!$A$2:$P$13,'Task 1'!C$14,FALSE)) -> The goal is to implement a new feature as described by a PR description | X5: =IF(VLOOKUP($A5,'Task 1'!$A$2:$P$13,'Task 1'!D$14,FALSE)="","",VLOOKUP($A5,'Task 1'!$A$2:$P$13,'Task 1'!D$14,FALSE)) -> No, the task was not completed. | Y5: =IF(VLOOKUP($A5,'Task 1'!$A$2:$P$13,'Task 1'!E$14,FALSE)="","",VLOOKUP($A5,'Task 1'!$A$2:$P$13,'Task 1'!E$14,FALSE)) -> Listing contents of a directory, reading a file writing to a file, creating a new file, modifying a file via diff syntax, running bash commands | Z5: =IF(VLOOKUP($A5,'Task 1'!$A$2:$P$13,'Task 1'!F$14,FALSE)="","",VLOOKUP($A5,'Task 1'!$A$2:$P$13,'Task 1'!F$14,FALSE)) -> Modifying the contents of a file | AA5: =IF(VLOOKUP($A5,'Task 1'!$A$2:$P$13,'Task 1'!G$14,FALSE)="","",VLOOKUP($A5,'Task 1'!$A$2:$P$13,'Task 1'!G$14,FALSE)) -> The agent has trouble fixing a syntax error (the indentation error) | AB5: =IF(VLOOKUP($A5,'Task 1'!$A$2:$P$13,'Task 1'!H$14,FALSE)="","",VLOOKUP($A5,'Task 1'!$A$2:$P$13,'Task 1'!H$14,FALSE)) -> The agent modified a part of the code that was not the erroneous part of the code. It tried multiple times to fix the indentation error by modifying a different part of the code. | AC5: =IF(VLOOKUP($A5,'Task 1'!$A$2:$P$13,'Task 1'!I$14,FALSE)="","",VLOOKUP($A5,'Task 1'!$A$2:$P$13,'Task 1'!I$14,FALSE)) -> 7 + from finance_tracker.income import IncomeTracker | AD5: =IF(VLOOKUP($A5,'Task 1'!$A$2:$P$13,'Task 1'!J$14,FALSE)="","",VLOOKUP($A5,'Task 1'!$A$2:$P$13,'Task 1'!J$14,FALSE)) -> income.py, expenses.py, reports.py, cli.py | ... AJ5: =IF(VLOOKUP($A5,'Task 1'!$A$2:$P$13,'Task 1'!P$14,FALSE)="","",VLOOKUP($A5,'Task 1'!$A$2:$P$13,'Task 1'!P$14,FALSE)) -> They are all modifying the same location of the code, which is not the location that needs a fix. Their purpose is to fix the indentation error, but the edits are the same. | AK5: =IF(VLOOKUP($A5,Form_Responses8[[Participant Key]:[Find and describe all potential bugs!]],3,FALSE)="","",VLOOKUP($A5,Form_Responses8[[Participant Key]:[Find and describe all potential bugs!]],3,FALSE)) -> It seems that the tool implementation is buggy and when the agent tries to modify the file, the process does not work correctly. From my inspections the agent tries to modify something, but the resulting file contents are not as expected. | AL5: =IF(VLOOKUP($A5,Form_Responses6[[Participant Key]:[Find and describe all potential bugs!]],3,FALSE)="","",VLOOKUP($A5,Form_Responses6[[Participant Key]:[Find and describe all potential bugs!]],3,FALSE)) -> The main issue is that the agent was never able to create a working dockerfile to try different approaches to resolve the problem. The main problem I see in this trajectory is that the error message from one write to a dockerfile was not returned to the agent. The other logic problem that could exist is that the agent seems to not have a good instruction on that it has to first create a dockerfile to be able to run all bash commands. | AM5: {=INDEX('Task 1'!$B$30:$B$43,COLUMN(A4))} -> 3 | AN5: {=INDEX('Task 1'!$B$30:$B$43,COLUMN(B4))} -> 1 | AO5: {=INDEX('Task 1'!$B$30:$B$43,COLUMN(C4))} -> 2 | AP5: {=INDEX('Task 1'!$B$30:$B$43,COLUMN(D4))} -> 1 | AQ5: {=INDEX('Task 1'!$B$30:$B$43,COLUMN(E4))} -> 1 | AR5: {=INDEX('Task 1'!$B$30:$B$43,COLUMN(F4))} -> 2 | AS5: {=INDEX('Task 1'!$B$30:$B$43,COLUMN(G4))} -> 1 | AT5: {=INDEX('Task 1'!$B$30:$B$43,COLUMN(H4))} -> 2 | ... AZ5: {=INDEX('Task 1'!$B$30:$B$43,COLUMN(N4))} -> 2 | BA5: 1 | BB5: 1 | BC5: ='Task 1'!$B$45 -> 21 | BD5: ='Task 1'!$D$45 -> 84
A6: ='Task 1'!A52 -> 33c6 | B6: =VLOOKUP(A6,'Task 1'!A$48:B$59,2,FALSE) -> A | C6: =VLOOKUP($A6,'Task 1'!$A$16:$P$27,'Task 1'!C$14,FALSE) -> 1 | D6: =VLOOKUP($A6,'Task 1'!$A$16:$P$27,'Task 1'!D$14,FALSE) -> 1 | E6: =VLOOKUP($A6,'Task 1'!$A$16:$P$27,'Task 1'!E$14,FALSE) -> 2 | F6: =VLOOKUP($A6,'Task 1'!$A$16:$P$27,'Task 1'!F$14,FALSE) -> 1 | G6: =VLOOKUP($A6,'Task 1'!$A$16:$P$27,'Task 1'!G$14,FALSE) -> 1 | H6: =VLOOKUP($A6,'Task 1'!$A$16:$P$27,'Task 1'!H$14,FALSE) -> 2 | I6: =VLOOKUP($A6,'Task 1'!$A$16:$P$27,'Task 1'!I$14,FALSE) -> 1 | J6: =VLOOKUP($A6,'Task 1'!$A$16:$P$27,'Task 1'!J$14,FALSE) -> 1 | ... P6: =VLOOKUP($A6,'Task 1'!$A$16:$P$27,'Task 1'!P$14,FALSE) -> 1 | Q6: =VLOOKUP($A6,'Task 2'!$A$2:$J$12,10,FALSE) -> 1 | R6: =VLOOKUP($A6,'Task 3'!$A$2:$J$12,10,FALSE) -> 1 | S6: =VLOOKUP($A6,'Task 1'!$A$16:$V$27,17,FALSE) -> 17 | T6: =VLOOKUP($A6,'Task 1'!$A$16:$V$27,18,FALSE) -> 74 | U6: =VLOOKUP($A6,'Task 1'!$A$16:$V$27,19,FALSE) -> 0.88095238 | V6: =VLOOKUP($A6,'Task 1'!$A$16:$W$27,23,FALSE) -> 0 | W6: =IF(VLOOKUP($A6,'Task 1'!$A$2:$P$13,'Task 1'!C$14,FALSE)="","",VLOOKUP($A6,'Task 1'!$A$2:$P$13,'Task 1'!C$14,FALSE)) -> Implementing a feature as suggested by a pull request | X6: =IF(VLOOKUP($A6,'Task 1'!$A$2:$P$13,'Task 1'!D$14,FALSE)="","",VLOOKUP($A6,'Task 1'!$A$2:$P$13,'Task 1'!D$14,FALSE)) -> No, the task was not completed. | Y6: =IF(VLOOKUP($A6,'Task 1'!$A$2:$P$13,'Task 1'!E$14,FALSE)="","",VLOOKUP($A6,'Task 1'!$A$2:$P$13,'Task 1'!E$14,FALSE)) -> listing files, showing file content, make modifications to files, create files, execute tests, install dependencies | Z6: =IF(VLOOKUP($A6,'Task 1'!$A$2:$P$13,'Task 1'!F$14,FALSE)="","",VLOOKUP($A6,'Task 1'!$A$2:$P$13,'Task 1'!F$14,FALSE)) -> editing files | AA6: =IF(VLOOKUP($A6,'Task 1'!$A$2:$P$13,'Task 1'!G$14,FALSE)="","",VLOOKUP($A6,'Task 1'!$A$2:$P$13,'Task 1'!G$14,FALSE)) -> Trying to add code to generate an income report. After multiple tries of making this change the tests always fail with an IndentationError. | AB6: =IF(VLOOKUP($A6,'Task 1'!$A$2:$P$13,'Task 1'!H$14,FALSE)="","",VLOOKUP($A6,'Task 1'!$A$2:$P$13,'Task 1'!H$14,FALSE)) -> The agent adds the code for generating an income report 6 times in a row before execution ends. It is always the same code change. | AC6: =IF(VLOOKUP($A6,'Task 1'!$A$2:$P$13,'Task 1'!I$14,FALSE)="","",VLOOKUP($A6,'Task 1'!$A$2:$P$13,'Task 1'!I$14,FALSE)) -> object {2} tool : str_replace_editor str_replace /finance_tracker/finance_tracker/cli.py --old_str 'from finance_tracker.reports import FinancialReport' --new_str 'from finance_tracker.reports import FinancialReport\nfrom finance_tracker.income import IncomeTracker' args : null | AD6: =IF(VLOOKUP($A6,'Task 1'!$A$2:$P$13,'Task 1'!J$14,FALSE)="","",VLOOKUP($A6,'Task 1'!$A$2:$P$13,'Task 1'!J$14,FALSE)) -> cli.py, reports.py, expenses.py, income.py | ... AJ6: =IF(VLOOKUP($A6,'Task 1'!$A$2:$P$13,'Task 1'!P$14,FALSE)="","",VLOOKUP($A6,'Task 1'!$A$2:$P$13,'Task 1'!P$14,FALSE)) -> They are all making the same change to cli.py. | AK6: =IF(VLOOKUP($A6,Form_Responses8[[Participant Key]:[Find and describe all potential bugs!]],3,FALSE)="","",VLOOKUP($A6,Form_Responses8[[Participant Key]:[Find and describe all potential bugs!]],3,FALSE)) -> The LLM calls the write_fix tool with a meaningful fix trying to modify the line 58 to also handle other line endings. There seems to however be a bug in the implementation of applying the proposed fix to the repository. The file is not correctly modified but the line to modify is only removed. | AL6: =IF(VLOOKUP($A6,Form_Responses6[[Participant Key]:[Find and describe all potential bugs!]],3,FALSE)="","",VLOOKUP($A6,Form_Responses6[[Participant Key]:[Find and describe all potential bugs!]],3,FALSE)) -> At the beginning the LLM tries to run a bash command to setup openjdk eventhough it is not allowed to do this at that state. In the second tool call it tries to run an unallowed command. The third LLM response is empty as the LLM rejects the prompt. Similar problems occur multiple times. The agent continues to fail to create a script for seting up the docker environment. After a while the LLM is able to successfully call the tool to write a docker file, but the agent fails to start the docker image. It tries this multiple more times but it is not clear why it fails. | AM6: {=INDEX('Task 1'!$B$30:$B$43,COLUMN(A5))} -> 3 | AN6: {=INDEX('Task 1'!$B$30:$B$43,COLUMN(B5))} -> 1 | AO6: {=INDEX('Task 1'!$B$30:$B$43,COLUMN(C5))} -> 2 | AP6: {=INDEX('Task 1'!$B$30:$B$43,COLUMN(D5))} -> 1 | AQ6: {=INDEX('Task 1'!$B$30:$B$43,COLUMN(E5))} -> 1 | AR6: {=INDEX('Task 1'!$B$30:$B$43,COLUMN(F5))} -> 2 | AS6: {=INDEX('Task 1'!$B$30:$B$43,COLUMN(G5))} -> 1 | AT6: {=INDEX('Task 1'!$B$30:$B$43,COLUMN(H5))} -> 2 | ... AZ6: {=INDEX('Task 1'!$B$30:$B$43,COLUMN(N5))} -> 2 | BA6: 1 | BB6: 1 | BC6: ='Task 1'!$B$45 -> 21 | BD6: ='Task 1'!$D$45 -> 84
A7: ='Task 1'!A53 -> 49f7 | B7: =VLOOKUP(A7,'Task 1'!A$48:B$59,2,FALSE) -> B | C7: =VLOOKUP($A7,'Task 1'!$A$16:$P$27,'Task 1'!C$14,FALSE) -> 2 | D7: =VLOOKUP($A7,'Task 1'!$A$16:$P$27,'Task 1'!D$14,FALSE) -> 1 | E7: =VLOOKUP($A7,'Task 1'!$A$16:$P$27,'Task 1'!E$14,FALSE) -> 2 | F7: =VLOOKUP($A7,'Task 1'!$A$16:$P$27,'Task 1'!F$14,FALSE) -> 1 | G7: =VLOOKUP($A7,'Task 1'!$A$16:$P$27,'Task 1'!G$14,FALSE) -> 1 | H7: =VLOOKUP($A7,'Task 1'!$A$16:$P$27,'Task 1'!H$14,FALSE) -> 2 | I7: =VLOOKUP($A7,'Task 1'!$A$16:$P$27,'Task 1'!I$14,FALSE) -> 0 | J7: =VLOOKUP($A7,'Task 1'!$A$16:$P$27,'Task 1'!J$14,FALSE) -> 0 | ... P7: =VLOOKUP($A7,'Task 1'!$A$16:$P$27,'Task 1'!P$14,FALSE) -> 1 | Q7: =VLOOKUP($A7,'Task 2'!$A$2:$J$12,10,FALSE) -> 0 | R7: =VLOOKUP($A7,'Task 3'!$A$2:$J$12,10,FALSE) -> 1 | S7: =VLOOKUP($A7,'Task 1'!$A$16:$V$27,17,FALSE) -> 16 | T7: =VLOOKUP($A7,'Task 1'!$A$16:$V$27,18,FALSE) -> 67 | U7: =VLOOKUP($A7,'Task 1'!$A$16:$V$27,19,FALSE) -> 0.79761905 | V7: =VLOOKUP($A7,'Task 1'!$A$16:$W$27,23,FALSE) -> 0.16666667 | W7: =IF(VLOOKUP($A7,'Task 1'!$A$2:$P$13,'Task 1'!C$14,FALSE)="","",VLOOKUP($A7,'Task 1'!$A$2:$P$13,'Task 1'!C$14,FALSE)) -> The agents goal is to add an income tracking feature to a personal finance tracker written in python | X7: =IF(VLOOKUP($A7,'Task 1'!$A$2:$P$13,'Task 1'!D$14,FALSE)="","",VLOOKUP($A7,'Task 1'!$A$2:$P$13,'Task 1'!D$14,FALSE)) -> No, the task was not completed. | Y7: =IF(VLOOKUP($A7,'Task 1'!$A$2:$P$13,'Task 1'!E$14,FALSE)="","",VLOOKUP($A7,'Task 1'!$A$2:$P$13,'Task 1'!E$14,FALSE)) -> Listing directories (ls), printing file contents (cat), writing file contents (str_replace_editor), running program (python3) | Z7: =IF(VLOOKUP($A7,'Task 1'!$A$2:$P$13,'Task 1'!F$14,FALSE)="","",VLOOKUP($A7,'Task 1'!$A$2:$P$13,'Task 1'!F$14,FALSE)) -> str_replace_editor (replacing parts of a file) | AA7: =IF(VLOOKUP($A7,'Task 1'!$A$2:$P$13,'Task 1'!G$14,FALSE)="","",VLOOKUP($A7,'Task 1'!$A$2:$P$13,'Task 1'!G$14,FALSE)) -> It is unable to indent properly (IndentationError) | AB7: =IF(VLOOKUP($A7,'Task 1'!$A$2:$P$13,'Task 1'!H$14,FALSE)="","",VLOOKUP($A7,'Task 1'!$A$2:$P$13,'Task 1'!H$14,FALSE)) -> Yes, it keeps "replacing" the line ' def do_generate_income_report(self, arg):' in /finance_tracker/cli.py with the same value, not knowing that the actual problem is that 'def __init__(self):' has no proper body. | AC7: =IF(VLOOKUP($A7,'Task 1'!$A$2:$P$13,'Task 1'!I$14,FALSE)="","",VLOOKUP($A7,'Task 1'!$A$2:$P$13,'Task 1'!I$14,FALSE)) -> --- a/finance_tracker/cli.py +++ b/finance_tracker/cli.py @@ -4,6 +4,7 @@ from finance_tracker.expenses import ExpenseTracker from finance_tracker.budgets import BudgetManager from finance_tracker.users import UserManager from finance_tracker.reports import FinancialReport +from finance_tracker.income import IncomeTracker from datetime import datetime class FinanceTrackerCLI(cmd.Cmd): (str_replace_editor str_replace /finance_tracker/finance_tracker/cli.py --old_str 'from finance_tracker.reports import FinancialReport' --new_str 'from finance_tracker.reports import FinancialReport) | AD7: =IF(VLOOKUP($A7,'Task 1'!$A$2:$P$13,'Task 1'!J$14,FALSE)="","",VLOOKUP($A7,'Task 1'!$A$2:$P$13,'Task 1'!J$14,FALSE)) -> cli.py, README.md | ... AJ7: =IF(VLOOKUP($A7,'Task 1'!$A$2:$P$13,'Task 1'!P$14,FALSE)="","",VLOOKUP($A7,'Task 1'!$A$2:$P$13,'Task 1'!P$14,FALSE)) -> The agent does the same changes five times, sometimes running the test in between and sometimes not | AK7: =IF(VLOOKUP($A7,Form_Responses8[[Participant Key]:[Find and describe all potential bugs!]],3,FALSE)="","",VLOOKUP($A7,Form_Responses8[[Participant Key]:[Find and describe all potential bugs!]],3,FALSE)) -> Test 'org.apache.commons.csv.CSVParserTest::testGetLineNumberWithCR' fails. However, the agent only is shown code from code from 'org.apache.commons.csv.CSVParserTest::testGetLineNumberWithCRLF' | AL7: =IF(VLOOKUP($A7,Form_Responses6[[Participant Key]:[Find and describe all potential bugs!]],3,FALSE)="","",VLOOKUP($A7,Form_Responses6[[Participant Key]:[Find and describe all potential bugs!]],3,FALSE)) -> Docker commands are not allowed on the system. The agent is told upfront that this is not possible, but it does it anyways. At first, it correctly uses write_to_file instead, but when the docker container fails to start for an unspecified reason, the agent tries to "escape" into a new shell that does not have this restriction or issues with the docker command. That is prohibited as well. ... | AM7: {=INDEX('Task 1'!$B$30:$B$43,COLUMN(A6))} -> 3 | AN7: {=INDEX('Task 1'!$B$30:$B$43,COLUMN(B6))} -> 1 | AO7: {=INDEX('Task 1'!$B$30:$B$43,COLUMN(C6))} -> 2 | AP7: {=INDEX('Task 1'!$B$30:$B$43,COLUMN(D6))} -> 1 | AQ7: {=INDEX('Task 1'!$B$30:$B$43,COLUMN(E6))} -> 1 | AR7: {=INDEX('Task 1'!$B$30:$B$43,COLUMN(F6))} -> 2 | AS7: {=INDEX('Task 1'!$B$30:$B$43,COLUMN(G6))} -> 1 | AT7: {=INDEX('Task 1'!$B$30:$B$43,COLUMN(H6))} -> 2 | ... AZ7: {=INDEX('Task 1'!$B$30:$B$43,COLUMN(N6))} -> 2 | BA7: 1 | BB7: 1 | BC7: ='Task 1'!$B$45 -> 21 | BD7: ='Task 1'!$D$45 -> 84
A8: ='Task 1'!A54 -> 536e | B8: =VLOOKUP(A8,'Task 1'!A$48:B$59,2,FALSE) -> A | C8: =VLOOKUP($A8,'Task 1'!$A$16:$P$27,'Task 1'!C$14,FALSE) -> 2 | D8: =VLOOKUP($A8,'Task 1'!$A$16:$P$27,'Task 1'!D$14,FALSE) -> 0 | E8: =VLOOKUP($A8,'Task 1'!$A$16:$P$27,'Task 1'!E$14,FALSE) -> 2 | F8: =VLOOKUP($A8,'Task 1'!$A$16:$P$27,'Task 1'!F$14,FALSE) -> 0 | G8: =VLOOKUP($A8,'Task 1'!$A$16:$P$27,'Task 1'!G$14,FALSE) -> 1 | H8: =VLOOKUP($A8,'Task 1'!$A$16:$P$27,'Task 1'!H$14,FALSE) -> 0 | I8: =VLOOKUP($A8,'Task 1'!$A$16:$P$27,'Task 1'!I$14,FALSE) -> 1 | J8: =VLOOKUP($A8,'Task 1'!$A$16:$P$27,'Task 1'!J$14,FALSE) -> 0 | ... P8: =VLOOKUP($A8,'Task 1'!$A$16:$P$27,'Task 1'!P$14,FALSE) -> 0 | Q8: =VLOOKUP($A8,'Task 2'!$A$2:$J$12,10,FALSE) -> 0 | R8: =VLOOKUP($A8,'Task 3'!$A$2:$J$12,10,FALSE) -> 0 | S8: =VLOOKUP($A8,'Task 1'!$A$16:$V$27,17,FALSE) -> 6 | T8: =VLOOKUP($A8,'Task 1'!$A$16:$V$27,18,FALSE) -> 22 | U8: =VLOOKUP($A8,'Task 1'!$A$16:$V$27,19,FALSE) -> 0.26190476 | V8: =VLOOKUP($A8,'Task 1'!$A$16:$W$27,23,FALSE) -> 0.75 | W8: =IF(VLOOKUP($A8,'Task 1'!$A$2:$P$13,'Task 1'!C$14,FALSE)="","",VLOOKUP($A8,'Task 1'!$A$2:$P$13,'Task 1'!C$14,FALSE)) -> income tracking feature as detailed in the PR description for the finance tracker project | X8: =IF(VLOOKUP($A8,'Task 1'!$A$2:$P$13,'Task 1'!D$14,FALSE)="","",VLOOKUP($A8,'Task 1'!$A$2:$P$13,'Task 1'!D$14,FALSE)) -> Yes, the task was completed successfully. | Y8: =IF(VLOOKUP($A8,'Task 1'!$A$2:$P$13,'Task 1'!E$14,FALSE)="","",VLOOKUP($A8,'Task 1'!$A$2:$P$13,'Task 1'!E$14,FALSE)) -> execute bash commands, tool call, file reading, update function | Z8: =IF(VLOOKUP($A8,'Task 1'!$A$2:$P$13,'Task 1'!F$14,FALSE)="","",VLOOKUP($A8,'Task 1'!$A$2:$P$13,'Task 1'!F$14,FALSE)) -> tool call | AA8: =IF(VLOOKUP($A8,'Task 1'!$A$2:$P$13,'Task 1'!G$14,FALSE)="","",VLOOKUP($A8,'Task 1'!$A$2:$P$13,'Task 1'!G$14,FALSE)) -> IndentationError, indicating a syntax error | AB8: =IF(VLOOKUP($A8,'Task 1'!$A$2:$P$13,'Task 1'!H$14,FALSE)="","",VLOOKUP($A8,'Task 1'!$A$2:$P$13,'Task 1'!H$14,FALSE)) -> Yes, he wanted to create a IncomeTracker class with different descriptions | AC8: =IF(VLOOKUP($A8,'Task 1'!$A$2:$P$13,'Task 1'!I$14,FALSE)="","",VLOOKUP($A8,'Task 1'!$A$2:$P$13,'Task 1'!I$14,FALSE)) -> replace a string in the File, altering the import statement for FinancialReport and adding IncomeTracker | AD8: =IF(VLOOKUP($A8,'Task 1'!$A$2:$P$13,'Task 1'!J$14,FALSE)="","",VLOOKUP($A8,'Task 1'!$A$2:$P$13,'Task 1'!J$14,FALSE)) -> report.py | ... AJ8: =IF(VLOOKUP($A8,'Task 1'!$A$2:$P$13,'Task 1'!P$14,FALSE)="","",VLOOKUP($A8,'Task 1'!$A$2:$P$13,'Task 1'!P$14,FALSE)) | AK8: =IF(VLOOKUP($A8,Form_Responses8[[Participant Key]:[Find and describe all potential bugs!]],3,FALSE)="","",VLOOKUP($A8,Form_Responses8[[Participant Key]:[Find and describe all potential bugs!]],3,FALSE)) -> The fix description from the agent isnt good enough for the LLM. | AL8: =IF(VLOOKUP($A8,Form_Responses6[[Participant Key]:[Find and describe all potential bugs!]],3,FALSE)="","",VLOOKUP($A8,Form_Responses6[[Participant Key]:[Find and describe all potential bugs!]],3,FALSE)) -> The command line could not handle the agents input. It repeats it self. | AM8: {=INDEX('Task 1'!$B$30:$B$43,COLUMN(A7))} -> 3 | AN8: {=INDEX('Task 1'!$B$30:$B$43,COLUMN(B7))} -> 1 | AO8: {=INDEX('Task 1'!$B$30:$B$43,COLUMN(C7))} -> 2 | AP8: {=INDEX('Task 1'!$B$30:$B$43,COLUMN(D7))} -> 1 | AQ8: {=INDEX('Task 1'!$B$30:$B$43,COLUMN(E7))} -> 1 | AR8: {=INDEX('Task 1'!$B$30:$B$43,COLUMN(F7))} -> 2 | AS8: {=INDEX('Task 1'!$B$30:$B$43,COLUMN(G7))} -> 1 | AT8: {=INDEX('Task 1'!$B$30:$B$43,COLUMN(H7))} -> 2 | ... AZ8: {=INDEX('Task 1'!$B$30:$B$43,COLUMN(N7))} -> 2 | BA8: 1 | BB8: 1 | BC8: ='Task 1'!$B$45 -> 21 | BD8: ='Task 1'!$D$45 -> 84
A9: ='Task 1'!A55 -> 5694 | B9: =VLOOKUP(A9,'Task 1'!A$48:B$59,2,FALSE) -> B | C9: =VLOOKUP($A9,'Task 1'!$A$16:$P$27,'Task 1'!C$14,FALSE) -> 3 | D9: =VLOOKUP($A9,'Task 1'!$A$16:$P$27,'Task 1'!D$14,FALSE) -> 1 | E9: =VLOOKUP($A9,'Task 1'!$A$16:$P$27,'Task 1'!E$14,FALSE) -> 1 | F9: =VLOOKUP($A9,'Task 1'!$A$16:$P$27,'Task 1'!F$14,FALSE) -> 0 | G9: =VLOOKUP($A9,'Task 1'!$A$16:$P$27,'Task 1'!G$14,FALSE) -> 0 | H9: =VLOOKUP($A9,'Task 1'!$A$16:$P$27,'Task 1'!H$14,FALSE) -> 0 | I9: =VLOOKUP($A9,'Task 1'!$A$16:$P$27,'Task 1'!I$14,FALSE) -> 0 | J9: =VLOOKUP($A9,'Task 1'!$A$16:$P$27,'Task 1'!J$14,FALSE) -> 0 | ... P9: =VLOOKUP($A9,'Task 1'!$A$16:$P$27,'Task 1'!P$14,FALSE) -> 0 | Q9: =VLOOKUP($A9,'Task 2'!$A$2:$J$12,10,FALSE) -> 0 | R9: =VLOOKUP($A9,'Task 3'!$A$2:$J$12,10,FALSE) -> 0 | S9: =VLOOKUP($A9,'Task 1'!$A$16:$V$27,17,FALSE) -> 9 | T9: =VLOOKUP($A9,'Task 1'!$A$16:$V$27,18,FALSE) -> 36 | U9: =VLOOKUP($A9,'Task 1'!$A$16:$V$27,19,FALSE) -> 0.42857143 | V9: =VLOOKUP($A9,'Task 1'!$A$16:$W$27,23,FALSE) -> 0.66666667 | W9: =IF(VLOOKUP($A9,'Task 1'!$A$2:$P$13,'Task 1'!C$14,FALSE)="","",VLOOKUP($A9,'Task 1'!$A$2:$P$13,'Task 1'!C$14,FALSE)) -> Enhance the `finance_tracker` project by adding income tracking functionality to complement the existing expense, budget, user, and reporting features. The feature allows users to record income sources, track income by category and date, calculate net balance, and integrate with reporting and CLI. | X9: =IF(VLOOKUP($A9,'Task 1'!$A$2:$P$13,'Task 1'!D$14,FALSE)="","",VLOOKUP($A9,'Task 1'!$A$2:$P$13,'Task 1'!D$14,FALSE)) -> No, the task was not completed. | Y9: =IF(VLOOKUP($A9,'Task 1'!$A$2:$P$13,'Task 1'!E$14,FALSE)="","",VLOOKUP($A9,'Task 1'!$A$2:$P$13,'Task 1'!E$14,FALSE)) -> Observations, replacements, package installation | Z9: =IF(VLOOKUP($A9,'Task 1'!$A$2:$P$13,'Task 1'!F$14,FALSE)="","",VLOOKUP($A9,'Task 1'!$A$2:$P$13,'Task 1'!F$14,FALSE)) -> Observations | AA9: =IF(VLOOKUP($A9,'Task 1'!$A$2:$P$13,'Task 1'!G$14,FALSE)="","",VLOOKUP($A9,'Task 1'!$A$2:$P$13,'Task 1'!G$14,FALSE)) -> FunctionCallingFormatError | AB9: =IF(VLOOKUP($A9,'Task 1'!$A$2:$P$13,'Task 1'!H$14,FALSE)="","",VLOOKUP($A9,'Task 1'!$A$2:$P$13,'Task 1'!H$14,FALSE)) -> The Agent requeries the model 3 times in a row after a FunctionCallingFormatError | AC9: =IF(VLOOKUP($A9,'Task 1'!$A$2:$P$13,'Task 1'!I$14,FALSE)="","",VLOOKUP($A9,'Task 1'!$A$2:$P$13,'Task 1'!I$14,FALSE)) -> - `add_income <amount> <category> <description> [tags] [recurring] [period]` - `generate_income_report [start_date] [end_date]` | AD9: =IF(VLOOKUP($A9,'Task 1'!$A$2:$P$13,'Task 1'!J$14,FALSE)="","",VLOOKUP($A9,'Task 1'!$A$2:$P$13,'Task 1'!J$14,FALSE)) -> cli.py, README.md | ... AJ9: =IF(VLOOKUP($A9,'Task 1'!$A$2:$P$13,'Task 1'!P$14,FALSE)="","",VLOOKUP($A9,'Task 1'!$A$2:$P$13,'Task 1'!P$14,FALSE)) -> The Agent compares two different versions of the cli.py file | AK9: =IF(VLOOKUP($A9,Form_Responses8[[Participant Key]:[Find and describe all potential bugs!]],3,FALSE)="","",VLOOKUP($A9,Form_Responses8[[Participant Key]:[Find and describe all potential bugs!]],3,FALSE)) -> it proposes the same fix over and over again. | AL9: =IF(VLOOKUP($A9,Form_Responses6[[Participant Key]:[Find and describe all potential bugs!]],3,FALSE)="","",VLOOKUP($A9,Form_Responses6[[Participant Key]:[Find and describe all potential bugs!]],3,FALSE)) -> Problem: it seems that the files which should be read have invalid syntax. The Agent is does not seem to be able to fix it... Potential Bug: The Bug seems to be related with java, maybe the installation failed, or java is not yet a environment variable. | AM9: {=INDEX('Task 1'!$B$30:$B$43,COLUMN(A8))} -> 3 | AN9: {=INDEX('Task 1'!$B$30:$B$43,COLUMN(B8))} -> 1 | AO9: {=INDEX('Task 1'!$B$30:$B$43,COLUMN(C8))} -> 2 | AP9: {=INDEX('Task 1'!$B$30:$B$43,COLUMN(D8))} -> 1 | AQ9: {=INDEX('Task 1'!$B$30:$B$43,COLUMN(E8))} -> 1 | AR9: {=INDEX('Task 1'!$B$30:$B$43,COLUMN(F8))} -> 2 | AS9: {=INDEX('Task 1'!$B$30:$B$43,COLUMN(G8))} -> 1 | AT9: {=INDEX('Task 1'!$B$30:$B$43,COLUMN(H8))} -> 2 | ... AZ9: {=INDEX('Task 1'!$B$30:$B$43,COLUMN(N8))} -> 2 | BA9: 1 | BB9: 1 | BC9: ='Task 1'!$B$45 -> 21 | BD9: ='Task 1'!$D$45 -> 84
A10: ='Task 1'!A56 -> bdb6 | B10: =VLOOKUP(A10,'Task 1'!A$48:B$59,2,FALSE) -> B | C10: =VLOOKUP($A10,'Task 1'!$A$16:$P$27,'Task 1'!C$14,FALSE) -> 0 | D10: =VLOOKUP($A10,'Task 1'!$A$16:$P$27,'Task 1'!D$14,FALSE) -> 1 | E10: =VLOOKUP($A10,'Task 1'!$A$16:$P$27,'Task 1'!E$14,FALSE) -> 2 | F10: =VLOOKUP($A10,'Task 1'!$A$16:$P$27,'Task 1'!F$14,FALSE) -> 0 | G10: =VLOOKUP($A10,'Task 1'!$A$16:$P$27,'Task 1'!G$14,FALSE) -> 1 | H10: =VLOOKUP($A10,'Task 1'!$A$16:$P$27,'Task 1'!H$14,FALSE) -> 2 | I10: =VLOOKUP($A10,'Task 1'!$A$16:$P$27,'Task 1'!I$14,FALSE) -> 1 | J10: =VLOOKUP($A10,'Task 1'!$A$16:$P$27,'Task 1'!J$14,FALSE) -> 0 | ... P10: =VLOOKUP($A10,'Task 1'!$A$16:$P$27,'Task 1'!P$14,FALSE) -> 1 | Q10: =VLOOKUP($A10,'Task 2'!$A$2:$J$12,10,FALSE) -> 0 | R10: =VLOOKUP($A10,'Task 3'!$A$2:$J$12,10,FALSE) -> 0 | S10: =VLOOKUP($A10,'Task 1'!$A$16:$V$27,17,FALSE) -> 14 | T10: =VLOOKUP($A10,'Task 1'!$A$16:$V$27,18,FALSE) -> 63 | U10: =VLOOKUP($A10,'Task 1'!$A$16:$V$27,19,FALSE) -> 0.75 | V10: =VLOOKUP($A10,'Task 1'!$A$16:$W$27,23,FALSE) -> 0.25 | W10: =IF(VLOOKUP($A10,'Task 1'!$A$2:$P$13,'Task 1'!C$14,FALSE)="","",VLOOKUP($A10,'Task 1'!$A$2:$P$13,'Task 1'!C$14,FALSE)) -> It's a helpful assistant that can interact with a computer to solve tasks. | X10: =IF(VLOOKUP($A10,'Task 1'!$A$2:$P$13,'Task 1'!D$14,FALSE)="","",VLOOKUP($A10,'Task 1'!$A$2:$P$13,'Task 1'!D$14,FALSE)) -> No, the task was not completed. | Y10: =IF(VLOOKUP($A10,'Task 1'!$A$2:$P$13,'Task 1'!E$14,FALSE)="","",VLOOKUP($A10,'Task 1'!$A$2:$P$13,'Task 1'!E$14,FALSE)) -> ls, cat, str_replace_editor, python3 | Z10: =IF(VLOOKUP($A10,'Task 1'!$A$2:$P$13,'Task 1'!F$14,FALSE)="","",VLOOKUP($A10,'Task 1'!$A$2:$P$13,'Task 1'!F$14,FALSE)) -> cat | AA10: =IF(VLOOKUP($A10,'Task 1'!$A$2:$P$13,'Task 1'!G$14,FALSE)="","",VLOOKUP($A10,'Task 1'!$A$2:$P$13,'Task 1'!G$14,FALSE)) -> IndentationError: expected an indented block after function definition on line 40 | AB10: =IF(VLOOKUP($A10,'Task 1'!$A$2:$P$13,'Task 1'!H$14,FALSE)="","",VLOOKUP($A10,'Task 1'!$A$2:$P$13,'Task 1'!H$14,FALSE)) -> The agent calls ls /finance_tracker/finance_tracker three times in succession, resulting in WARNING | AC10: =IF(VLOOKUP($A10,'Task 1'!$A$2:$P$13,'Task 1'!I$14,FALSE)="","",VLOOKUP($A10,'Task 1'!$A$2:$P$13,'Task 1'!I$14,FALSE)) -> str_replace_editor str_replace /finance_tracker/finance_tracker/cli.py --old_str 'from finance_tracker.reports import FinancialReport' --new_str 'from finance_tracker.reports import FinancialReport | AD10: =IF(VLOOKUP($A10,'Task 1'!$A$2:$P$13,'Task 1'!J$14,FALSE)="","",VLOOKUP($A10,'Task 1'!$A$2:$P$13,'Task 1'!J$14,FALSE)) -> /finance_tracker/finance_tracker/cli.py | ... AJ10: =IF(VLOOKUP($A10,'Task 1'!$A$2:$P$13,'Task 1'!P$14,FALSE)="","",VLOOKUP($A10,'Task 1'!$A$2:$P$13,'Task 1'!P$14,FALSE)) -> They are the exact same change | AK10: =IF(VLOOKUP($A10,Form_Responses8[[Participant Key]:[Find and describe all potential bugs!]],3,FALSE)="","",VLOOKUP($A10,Form_Responses8[[Participant Key]:[Find and describe all potential bugs!]],3,FALSE)) -> I do not see an fatal bug but continued warning of repetition detected! with repeated write_fix seems concerning. The core should give more drastic guidance or the warning is not effective. | AL10: =IF(VLOOKUP($A10,Form_Responses6[[Participant Key]:[Find and describe all potential bugs!]],3,FALSE)="","",VLOOKUP($A10,Form_Responses6[[Participant Key]:[Find and describe all potential bugs!]],3,FALSE)) -> I don't see any obvious problem with agent's logic. | AM10: {=INDEX('Task 1'!$B$30:$B$43,COLUMN(A9))} -> 3 | AN10: {=INDEX('Task 1'!$B$30:$B$43,COLUMN(B9))} -> 1 | AO10: {=INDEX('Task 1'!$B$30:$B$43,COLUMN(C9))} -> 2 | AP10: {=INDEX('Task 1'!$B$30:$B$43,COLUMN(D9))} -> 1 | AQ10: {=INDEX('Task 1'!$B$30:$B$43,COLUMN(E9))} -> 1 | AR10: {=INDEX('Task 1'!$B$30:$B$43,COLUMN(F9))} -> 2 | AS10: {=INDEX('Task 1'!$B$30:$B$43,COLUMN(G9))} -> 1 | AT10: {=INDEX('Task 1'!$B$30:$B$43,COLUMN(H9))} -> 2 | ... AZ10: {=INDEX('Task 1'!$B$30:$B$43,COLUMN(N9))} -> 2 | BA10: 1 | BB10: 1 | BC10: ='Task 1'!$B$45 -> 21 | BD10: ='Task 1'!$D$45 -> 84
A11: ='Task 1'!A57 -> bdf7 | B11: =VLOOKUP(A11,'Task 1'!A$48:B$59,2,FALSE) -> A | C11: =VLOOKUP($A11,'Task 1'!$A$16:$P$27,'Task 1'!C$14,FALSE) -> 0 | D11: =VLOOKUP($A11,'Task 1'!$A$16:$P$27,'Task 1'!D$14,FALSE) -> 1 | E11: =VLOOKUP($A11,'Task 1'!$A$16:$P$27,'Task 1'!E$14,FALSE) -> 2 | F11: =VLOOKUP($A11,'Task 1'!$A$16:$P$27,'Task 1'!F$14,FALSE) -> 1 | G11: =VLOOKUP($A11,'Task 1'!$A$16:$P$27,'Task 1'!G$14,FALSE) -> 0 | H11: =VLOOKUP($A11,'Task 1'!$A$16:$P$27,'Task 1'!H$14,FALSE) -> 0 | I11: =VLOOKUP($A11,'Task 1'!$A$16:$P$27,'Task 1'!I$14,FALSE) -> 0 | J11: =VLOOKUP($A11,'Task 1'!$A$16:$P$27,'Task 1'!J$14,FALSE) -> 0 | ... P11: =VLOOKUP($A11,'Task 1'!$A$16:$P$27,'Task 1'!P$14,FALSE) -> 0 | Q11: =VLOOKUP($A11,'Task 2'!$A$2:$J$12,10,FALSE) -> 1 | R11: =VLOOKUP($A11,'Task 3'!$A$2:$J$12,10,FALSE) -> 0 | S11: =VLOOKUP($A11,'Task 1'!$A$16:$V$27,17,FALSE) -> 4 | T11: =VLOOKUP($A11,'Task 1'!$A$16:$V$27,18,FALSE) -> 18 | U11: =VLOOKUP($A11,'Task 1'!$A$16:$V$27,19,FALSE) -> 0.21428571 | V11: =VLOOKUP($A11,'Task 1'!$A$16:$W$27,23,FALSE) -> 0.83333333 | W11: =IF(VLOOKUP($A11,'Task 1'!$A$2:$P$13,'Task 1'!C$14,FALSE)="","",VLOOKUP($A11,'Task 1'!$A$2:$P$13,'Task 1'!C$14,FALSE)) -> The agent's goal is to implement an finance tracker application by creating and testing the required functionalities. | X11: =IF(VLOOKUP($A11,'Task 1'!$A$2:$P$13,'Task 1'!D$14,FALSE)="","",VLOOKUP($A11,'Task 1'!$A$2:$P$13,'Task 1'!D$14,FALSE)) -> No, the task was not completed. | Y11: =IF(VLOOKUP($A11,'Task 1'!$A$2:$P$13,'Task 1'!E$14,FALSE)="","",VLOOKUP($A11,'Task 1'!$A$2:$P$13,'Task 1'!E$14,FALSE)) -> Read content, Implement code, Test code, and fix code | Z11: =IF(VLOOKUP($A11,'Task 1'!$A$2:$P$13,'Task 1'!F$14,FALSE)="","",VLOOKUP($A11,'Task 1'!$A$2:$P$13,'Task 1'!F$14,FALSE)) -> Fix code | AA11: =IF(VLOOKUP($A11,'Task 1'!$A$2:$P$13,'Task 1'!G$14,FALSE)="","",VLOOKUP($A11,'Task 1'!$A$2:$P$13,'Task 1'!G$14,FALSE)) -> The agent has trouble implementing a correct version of the income tracker | AB11: =IF(VLOOKUP($A11,'Task 1'!$A$2:$P$13,'Task 1'!H$14,FALSE)="","",VLOOKUP($A11,'Task 1'!$A$2:$P$13,'Task 1'!H$14,FALSE)) -> Create the `IncomeTracker` class in `income.py` and update related files in the `finance_tracker` directory to incorporate income tracking features as outlined in the PR description. | AC11: =IF(VLOOKUP($A11,'Task 1'!$A$2:$P$13,'Task 1'!I$14,FALSE)="","",VLOOKUP($A11,'Task 1'!$A$2:$P$13,'Task 1'!I$14,FALSE)) -> The file /finance_tracker/finance_tracker/cli.py has been edited. Here's the result of running `cat -n` on a snippet of /finance_tracker/finance_tracker/cli.py: The file /finance_tracker/finance_tracker/reports.py has been edited. Here's the result of running `cat -n` on a snippet of /finance_tracker/finance_tracker/reports.py: 1 import cmd 32 "period": f"{start_date or 'all'} to {end_date or 'all'}", 2 import argparse 33 "category_totals": categories, 3 from finance_tracker.expenses import ExpenseTracker 34 "total": sum(categories.values()) 4 from finance_tracker.budgets import BudgetManager 35 } 5 from finance_tracker.users import UserManager 36 6 from finance_tracker.reports import FinancialReport 37 def generate_income_summary(self, start_date: str = None, end_date: str = None) -> Dict: 7 from finance_tracker.income import IncomeTracker 38 """Generate a summary of income by category.""" 8 from datetime import datetime 39 incomes = self.income_tracker.incomes 9 40 if start_date and end_date: 10 class FinanceTrackerCLI(cmd.Cmd): 41 incomes = [inc for inc in incomes if start_date <= inc.date <= end_date] 42 categories = {} 43 for inc in incomes: 44 cat = inc.category 45 categories[cat] = categories.get(cat, 0.0) + inc.amount 46 return { 47 "user_id": self.user_id, 48 "period": f"{start_date or 'all'} to {end_date or 'all'}", 49 "category_totals": categories, 50 "total": sum(categories.values()) 51 } 52 53 def generate_budget_comparison(self, period: str = "monthly") -> List[Dict]: 54 """Compare spending against budgets.""" 55 budgets = self.budget_manager.get_all_budgets() 56 comparison = [] Review the changes and make sure they are as expected. Edit the file again if necessary. Review the changes and make sure they are as expected. Edit the file again if necessary. | AD11: =IF(VLOOKUP($A11,'Task 1'!$A$2:$P$13,'Task 1'!J$14,FALSE)="","",VLOOKUP($A11,'Task 1'!$A$2:$P$13,'Task 1'!J$14,FALSE)) -> cli.py | ... AJ11: =IF(VLOOKUP($A11,'Task 1'!$A$2:$P$13,'Task 1'!P$14,FALSE)="","",VLOOKUP($A11,'Task 1'!$A$2:$P$13,'Task 1'!P$14,FALSE)) | AK11: =IF(VLOOKUP($A11,Form_Responses8[[Participant Key]:[Find and describe all potential bugs!]],3,FALSE)="","",VLOOKUP($A11,Form_Responses8[[Participant Key]:[Find and describe all potential bugs!]],3,FALSE)) -> The agent calls the write_fix tool to fix the problem but nothing is changed | AL11: =IF(VLOOKUP($A11,Form_Responses6[[Participant Key]:[Find and describe all potential bugs!]],3,FALSE)="","",VLOOKUP($A11,Form_Responses6[[Participant Key]:[Find and describe all potential bugs!]],3,FALSE)) -> The agent executes commands that are not available or allowed | AM11: {=INDEX('Task 1'!$B$30:$B$43,COLUMN(A10))} -> 3 | AN11: {=INDEX('Task 1'!$B$30:$B$43,COLUMN(B10))} -> 1 | AO11: {=INDEX('Task 1'!$B$30:$B$43,COLUMN(C10))} -> 2 | AP11: {=INDEX('Task 1'!$B$30:$B$43,COLUMN(D10))} -> 1 | AQ11: {=INDEX('Task 1'!$B$30:$B$43,COLUMN(E10))} -> 1 | AR11: {=INDEX('Task 1'!$B$30:$B$43,COLUMN(F10))} -> 2 | AS11: {=INDEX('Task 1'!$B$30:$B$43,COLUMN(G10))} -> 1 | AT11: {=INDEX('Task 1'!$B$30:$B$43,COLUMN(H10))} -> 2 | ... AZ11: {=INDEX('Task 1'!$B$30:$B$43,COLUMN(N10))} -> 2 | BA11: 1 | BB11: 1 | BC11: ='Task 1'!$B$45 -> 21 | BD11: ='Task 1'!$D$45 -> 84
A12: ='Task 1'!A58 -> 18e7 | B12: =VLOOKUP(A12,'Task 1'!A$48:B$59,2,FALSE) -> A | C12: =VLOOKUP($A12,'Task 1'!$A$16:$P$27,'Task 1'!C$14,FALSE) -> 2 | D12: =VLOOKUP($A12,'Task 1'!$A$16:$P$27,'Task 1'!D$14,FALSE) -> 0 | E12: =VLOOKUP($A12,'Task 1'!$A$16:$P$27,'Task 1'!E$14,FALSE) -> 2 | F12: =VLOOKUP($A12,'Task 1'!$A$16:$P$27,'Task 1'!F$14,FALSE) -> 1 | G12: =VLOOKUP($A12,'Task 1'!$A$16:$P$27,'Task 1'!G$14,FALSE) -> 1 | H12: =VLOOKUP($A12,'Task 1'!$A$16:$P$27,'Task 1'!H$14,FALSE) -> 2 | I12: =VLOOKUP($A12,'Task 1'!$A$16:$P$27,'Task 1'!I$14,FALSE) -> 0 | J12: =VLOOKUP($A12,'Task 1'!$A$16:$P$27,'Task 1'!J$14,FALSE) -> 1 | ... P12: =VLOOKUP($A12,'Task 1'!$A$16:$P$27,'Task 1'!P$14,FALSE) -> 1 | Q12: =VLOOKUP($A12,'Task 2'!$A$2:$J$12,10,FALSE) -> #N/A | R12: =VLOOKUP($A12,'Task 3'!$A$2:$J$12,10,FALSE) -> #N/A | S12: =VLOOKUP($A12,'Task 1'!$A$16:$V$27,17,FALSE) -> 15 | T12: =VLOOKUP($A12,'Task 1'!$A$16:$V$27,18,FALSE) -> 58 | U12: =VLOOKUP($A12,'Task 1'!$A$16:$V$27,19,FALSE) -> 0.69047619 | V12: =VLOOKUP($A12,'Task 1'!$A$16:$W$27,23,FALSE) -> 0.33333333 | W12: =IF(VLOOKUP($A12,'Task 1'!$A$2:$P$13,'Task 1'!C$14,FALSE)="","",VLOOKUP($A12,'Task 1'!$A$2:$P$13,'Task 1'!C$14,FALSE)) -> The agent goal is to implement new feature or new function-ality- that was described in the PR specifically the income tracking feature for a finance tracker project. | X12: =IF(VLOOKUP($A12,'Task 1'!$A$2:$P$13,'Task 1'!D$14,FALSE)="","",VLOOKUP($A12,'Task 1'!$A$2:$P$13,'Task 1'!D$14,FALSE)) -> Yes, the task was completed successfully. | Y12: =IF(VLOOKUP($A12,'Task 1'!$A$2:$P$13,'Task 1'!E$14,FALSE)="","",VLOOKUP($A12,'Task 1'!$A$2:$P$13,'Task 1'!E$14,FALSE)) -> File editing, File listing, Executing commands such as execute script and install package | Z12: =IF(VLOOKUP($A12,'Task 1'!$A$2:$P$13,'Task 1'!F$14,FALSE)="","",VLOOKUP($A12,'Task 1'!$A$2:$P$13,'Task 1'!F$14,FALSE)) -> File editing | AA12: =IF(VLOOKUP($A12,'Task 1'!$A$2:$P$13,'Task 1'!G$14,FALSE)="","",VLOOKUP($A12,'Task 1'!$A$2:$P$13,'Task 1'!G$14,FALSE)) -> Correctly editing the file? as there are many indentation errors… | AB12: =IF(VLOOKUP($A12,'Task 1'!$A$2:$P$13,'Task 1'!H$14,FALSE)="","",VLOOKUP($A12,'Task 1'!$A$2:$P$13,'Task 1'!H$14,FALSE)) -> Yes there was some repetition, e.g, repeated listing of files at the start | AC12: =IF(VLOOKUP($A12,'Task 1'!$A$2:$P$13,'Task 1'!I$14,FALSE)="","",VLOOKUP($A12,'Task 1'!$A$2:$P$13,'Task 1'!I$14,FALSE)) -> 1 import cmd 2 import argparse 3 from finance_tracker.expenses import ExpenseTracker 4 from finance_tracker.budgets import BudgetManager 5 from finance_tracker.users import UserManager 6 from finance_tracker.reports import FinancialReport 7 from finance_tracker.income import IncomeTracker 8 from datetime import datetime 9 10 class FinanceTrackerCLI(cmd.Cmd): 11 """Command-line interface for the finance tracker.""" 12 prompt = "FinanceTracker> " 13 intro = "Welcome to the Personal Finance Tracker. Type 'help' for commands." 14 15 def __init__(self): 16 super().__init__() 17 self.user_manager = UserManager() 18 self.current_user = None 19 self.expense_tracker = None 20 self.budget_manager = None 21 self.report_generator = None 22 23 def do_login(self, arg): 24 """Login to the system: login <username> <password>""" 25 args = arg.split() 26 if len(args) != 2: 27 print("Usage: login <username> <password>") 28 return 29 username, password = args 30 if self.user_manager.authenticate_user(username, password): 31 self.current_user = username 32 self.expense_tracker = ExpenseTracker(username) 33 self.budget_manager = BudgetManager(username) 34 self.report_generator = FinancialReport(username, self.expense_tracker, self.budget_manager) 35 print(f"Logged in as {username}") 36 else: 37 print("Invalid username or password") 38 39 def do_register(self, arg): 40 """Register a new user: register <username> <password> <email>""" 41 args = arg.split() 42 if len(args) != 3: 43 print("Usage: register <username> <password> <email>") 44 return 45 try: 46 self.user_manager.register_user(*args) 47 print(f"User {args[0]} registered successfully") 48 except ValueError as e: 49 print(f"Error: {e}") 50 51 def do_add_expense(self, arg): 52 """Add an expense: add_expense <amount> <category> <description> [tags] [recurring] [period]""" 53 if not self.current_user: 54 print("Please login first") 55 return 56 args = arg.split() 57 if len(args) < 3: 58 print("Usage: add_expense <amount> <category> <description> [tags] [recurring] [period]") 59 return 60 amount, category, description = args[:3] 61 tags = args[3].split(",") if len(args) > 3 else [] 62 is_recurring = args[4].lower() == "true" if len(args) > 4 else False 63 period = args[5] if len(args) > 5 else None 64 try: 65 expense_id = self.expense_tracker.add_expense(float(amount), category, description, 66 tags=tags, is_recurring=is_recurring, 67 recurrence_period=period) 68 print(f"Expense added with ID: {expense_id}") 69 except ValueError as e: 70 print(f"Error: {e}") 71 72 def do_set_budget(self, arg): 73 """Set a budget: set_budget <category> <amount> [period] [alert_threshold]""" 74 if not self.current_user: 75 print("Please login first") 76 return 77 args = arg.split() 78 if len(args) < 2: 79 print("Usage: set_budget <category> <amount> [period] [alert_threshold]") 80 return 81 category, amount = args[:2] 82 period = args[2] if len(args) > 2 else "monthly" 83 alert_threshold = float(args[3]) if len(args) > 3 else 0.8 84 try: 85 self.budget_manager.set_budget(category, float(amount), period, alert_threshold) 86 print(f"Budget set for {category} ({period})") 87 except ValueError as e: 88 print(f"Error: {e}") 89 90 def do_generate_report(self, arg): 91 """Generate a report: generate_report <type> [start_date] [end_date]""" 92 if not self.current_user: 93 print("Please login first") 94 return 95 args = arg.split() 96 if len(args) < 1: 97 print("Usage: generate_report <type> [start_date] [end_date]") 98 return 99 report_type = args[0] 100 start_date = args[1] if len(args) > 1 else None 101 end_date = args[2] if len(args) > 2 else None 102 try: 103 report_file = self.report_generator.generate_report_pdf(report_type, start_date, end_date) 104 print(f"Report generated: {report_file}") 105 except Exception as e: 106 print(f"Error: {e}") 107 108 def do_exit(self, arg): 109 """Exit the CLI.""" 110 print("Goodbye!") 111 return True 112 113 def preloop(self): 114 """Initialize CLI state.""" 115 print("Personal Finance Tracker CLI. Type 'register' or 'login' to begin.") | AD12: =IF(VLOOKUP($A12,'Task 1'!$A$2:$P$13,'Task 1'!J$14,FALSE)="","",VLOOKUP($A12,'Task 1'!$A$2:$P$13,'Task 1'!J$14,FALSE)) -> income.py, expenses.py, reports.py, cli.py, README, | ... AJ12: =IF(VLOOKUP($A12,'Task 1'!$A$2:$P$13,'Task 1'!P$14,FALSE)="","",VLOOKUP($A12,'Task 1'!$A$2:$P$13,'Task 1'!P$14,FALSE)) -> From the diff comparison they look similar | AK12: =IF(VLOOKUP($A12,Form_Responses8[[Participant Key]:[Find and describe all potential bugs!]],3,FALSE)="","",VLOOKUP($A12,Form_Responses8[[Participant Key]:[Find and describe all potential bugs!]],3,FALSE)) -> #N/A | AL12: =IF(VLOOKUP($A12,Form_Responses6[[Participant Key]:[Find and describe all potential bugs!]],3,FALSE)="","",VLOOKUP($A12,Form_Responses6[[Participant Key]:[Find and describe all potential bugs!]],3,FALSE)) -> #N/A | AM12: {=INDEX('Task 1'!$B$30:$B$43,COLUMN(A11))} -> 3 | AN12: {=INDEX('Task 1'!$B$30:$B$43,COLUMN(B11))} -> 1 | AO12: {=INDEX('Task 1'!$B$30:$B$43,COLUMN(C11))} -> 2 | AP12: {=INDEX('Task 1'!$B$30:$B$43,COLUMN(D11))} -> 1 | AQ12: {=INDEX('Task 1'!$B$30:$B$43,COLUMN(E11))} -> 1 | AR12: {=INDEX('Task 1'!$B$30:$B$43,COLUMN(F11))} -> 2 | AS12: {=INDEX('Task 1'!$B$30:$B$43,COLUMN(G11))} -> 1 | AT12: {=INDEX('Task 1'!$B$30:$B$43,COLUMN(H11))} -> 2 | ... AZ12: {=INDEX('Task 1'!$B$30:$B$43,COLUMN(N11))} -> 2 | BA12: 1 | BB12: 1 | BC12: ='Task 1'!$B$45 -> 21 | BD12: ='Task 1'!$D$45 -> 84
A13: ='Task 1'!A59 -> e43c | B13: =VLOOKUP(A13,'Task 1'!A$48:B$59,2,FALSE) -> B | C13: =VLOOKUP($A13,'Task 1'!$A$16:$P$27,'Task 1'!C$14,FALSE) -> 1 | D13: =VLOOKUP($A13,'Task 1'!$A$16:$P$27,'Task 1'!D$14,FALSE) -> 1 | E13: =VLOOKUP($A13,'Task 1'!$A$16:$P$27,'Task 1'!E$14,FALSE) -> 2 | F13: =VLOOKUP($A13,'Task 1'!$A$16:$P$27,'Task 1'!F$14,FALSE) -> 0 | G13: =VLOOKUP($A13,'Task 1'!$A$16:$P$27,'Task 1'!G$14,FALSE) -> 1 | H13: =VLOOKUP($A13,'Task 1'!$A$16:$P$27,'Task 1'!H$14,FALSE) -> 1 | I13: =VLOOKUP($A13,'Task 1'!$A$16:$P$27,'Task 1'!I$14,FALSE) -> 1 | J13: =VLOOKUP($A13,'Task 1'!$A$16:$P$27,'Task 1'!J$14,FALSE) -> 0 | ... P13: =VLOOKUP($A13,'Task 1'!$A$16:$P$27,'Task 1'!P$14,FALSE) -> 1 | Q13: =VLOOKUP($A13,'Task 2'!$A$2:$J$12,10,FALSE) -> 1 | R13: =VLOOKUP($A13,'Task 3'!$A$2:$J$12,10,FALSE) -> 0 | S13: =VLOOKUP($A13,'Task 1'!$A$16:$V$27,17,FALSE) -> 13 | T13: =VLOOKUP($A13,'Task 1'!$A$16:$V$27,18,FALSE) -> 56 | U13: =VLOOKUP($A13,'Task 1'!$A$16:$V$27,19,FALSE) -> 0.66666667 | V13: =VLOOKUP($A13,'Task 1'!$A$16:$W$27,23,FALSE) -> 0.41666667 | W13: =IF(VLOOKUP($A13,'Task 1'!$A$2:$P$13,'Task 1'!C$14,FALSE)="","",VLOOKUP($A13,'Task 1'!$A$2:$P$13,'Task 1'!C$14,FALSE)) -> The agent goal is to implement necessary changes following the requirements in a pull requests. It will need to first analyses this task step by step and provide candidate solutions. Then, they need to run tools to validate the correctness of candidates solutions. Finally, they will submit the solutions if they pass the validation. | X13: =IF(VLOOKUP($A13,'Task 1'!$A$2:$P$13,'Task 1'!D$14,FALSE)="","",VLOOKUP($A13,'Task 1'!$A$2:$P$13,'Task 1'!D$14,FALSE)) -> No, the task was not completed. | Y13: =IF(VLOOKUP($A13,'Task 1'!$A$2:$P$13,'Task 1'!E$14,FALSE)="","",VLOOKUP($A13,'Task 1'!$A$2:$P$13,'Task 1'!E$14,FALSE)) -> run tools, generate solutions, fix solutions, submit solutions | Z13: =IF(VLOOKUP($A13,'Task 1'!$A$2:$P$13,'Task 1'!F$14,FALSE)="","",VLOOKUP($A13,'Task 1'!$A$2:$P$13,'Task 1'!F$14,FALSE)) -> run tools | AA13: =IF(VLOOKUP($A13,'Task 1'!$A$2:$P$13,'Task 1'!G$14,FALSE)="","",VLOOKUP($A13,'Task 1'!$A$2:$P$13,'Task 1'!G$14,FALSE)) -> The agent has trouble on generating compilable code. Some errors include "ModuleNotFoundError", indicating they fail to setup environment correctly, and "IndentationError", indicating they fails to generate syntactically correct code. | AB13: =IF(VLOOKUP($A13,'Task 1'!$A$2:$P$13,'Task 1'!H$14,FALSE)="","",VLOOKUP($A13,'Task 1'!$A$2:$P$13,'Task 1'!H$14,FALSE)) -> Yes, the agent run programs, found some face indentation errors and then fixing these errors 4 times in a row before stopping. | AC13: =IF(VLOOKUP($A13,'Task 1'!$A$2:$P$13,'Task 1'!I$14,FALSE)="","",VLOOKUP($A13,'Task 1'!$A$2:$P$13,'Task 1'!I$14,FALSE)) -> +from finance_tracker.income import IncomeTracker | AD13: =IF(VLOOKUP($A13,'Task 1'!$A$2:$P$13,'Task 1'!J$14,FALSE)="","",VLOOKUP($A13,'Task 1'!$A$2:$P$13,'Task 1'!J$14,FALSE)) -> /finance_tracker/finance_tracker/cli.py | ... AJ13: =IF(VLOOKUP($A13,'Task 1'!$A$2:$P$13,'Task 1'!P$14,FALSE)="","",VLOOKUP($A13,'Task 1'!$A$2:$P$13,'Task 1'!P$14,FALSE)) -> They tried to fix same error and return same fix for all turns. | AK13: =IF(VLOOKUP($A13,Form_Responses8[[Participant Key]:[Find and describe all potential bugs!]],3,FALSE)="","",VLOOKUP($A13,Form_Responses8[[Participant Key]:[Find and describe all potential bugs!]],3,FALSE)) -> The write_fix() tool should generate the patch and apply this patch to current repository by modifying the read() method. However, I guess it only generate the fix and do not apply into current repository. That is reason why the test results are always failures. | AL13: =IF(VLOOKUP($A13,Form_Responses6[[Participant Key]:[Find and describe all potential bugs!]],3,FALSE)="","",VLOOKUP($A13,Form_Responses6[[Participant Key]:[Find and describe all potential bugs!]],3,FALSE)) -> I think the error lies on tool design to execute command. This based on the observation that this error message "SYSTEM: Unable to execute command" repeat 39 times in the logs. Without executing the command, the agent cannot define the next steps, leading to failures. | AM13: {=INDEX('Task 1'!$B$30:$B$43,COLUMN(A12))} -> 3 | AN13: {=INDEX('Task 1'!$B$30:$B$43,COLUMN(B12))} -> 1 | AO13: {=INDEX('Task 1'!$B$30:$B$43,COLUMN(C12))} -> 2 | AP13: {=INDEX('Task 1'!$B$30:$B$43,COLUMN(D12))} -> 1 | AQ13: {=INDEX('Task 1'!$B$30:$B$43,COLUMN(E12))} -> 1 | AR13: {=INDEX('Task 1'!$B$30:$B$43,COLUMN(F12))} -> 2 | AS13: {=INDEX('Task 1'!$B$30:$B$43,COLUMN(G12))} -> 1 | AT13: {=INDEX('Task 1'!$B$30:$B$43,COLUMN(H12))} -> 2 | ... AZ13: {=INDEX('Task 1'!$B$30:$B$43,COLUMN(N12))} -> 2 | BA13: 1 | BB13: 1 | BC13: ='Task 1'!$B$45 -> 21 | BD13: ='Task 1'!$D$45 -> 84

Sheet CSV Results
A1: Participant Key | B1: Group | C1: Familiarity Level | D1: Task 1 Performance % | E1: Task 1 Time | F1: Task 2 Score | G1: Task 2 Time | H1: Task 3 Score | I1: Task 3 Time | J1: Task 1 Mental Demand | K1: Task 1 Temporal Demand | L1: Task 1 Perceived Perf. | M1: Task 1 Effort | N1: Task 1 Frustration | O1: Task 2 Mental Demand | P1: Task 2 Temporal Demand | Q1: Task 2 Perceived Perf. | R1: Task 2 Effort | S1: Task 2 Frustration | T1: Task 3 Mental Demand | U1: Task 3 Temporal Demand | V1: Task 3 Perceived Perf. | W1: Task 3 Effort | X1: Task 3 Frustration
A2: ='Task 1'!A48 -> fe6c | B2: =VLOOKUP('CSV Results'!A2,'Task 1'!$A$48:$B$59,2,FALSE) -> B | C2: =VLOOKUP(A2,'Task 1'!A$74:B$85,2,FALSE) -> Basic | D2: =VLOOKUP($A2,'Task 1'!$A$16:$V$27,19,FALSE) -> 0.60714286 | E2: =MINUTE(VLOOKUP($A2,'Task 1'!$A$16:$V$27,22,FALSE))+SECOND(VLOOKUP($A2,'Task 1'!$A$16:$V$27,22,FALSE))/60 -> 25 | F2: =VLOOKUP($A2,'Task 2'!$A$2:$J$12,10,FALSE) -> 0 | G2: =MINUTE(VLOOKUP($A2,'Task 2'!$A$2:$J$12,2,FALSE))+SECOND(VLOOKUP($A2,'Task 2'!$A$2:$J$12,2,FALSE))/60 -> 12 | H2: =VLOOKUP($A2,'Task 3'!$A$2:$J$12,10,FALSE) -> 0 | I2: =MINUTE(VLOOKUP($A2,'Task 3'!$A$2:$J$12,2,FALSE))+SECOND(VLOOKUP($A2,'Task 3'!$A$2:$J$12,2,FALSE))/60 -> 12 | J2: =VLOOKUP($A2,Form_Responses[],17,FALSE) -> 6 | K2: =VLOOKUP($A2,Form_Responses[],18,FALSE) -> 5 | L2: =VLOOKUP($A2,Form_Responses[],19,FALSE) -> 4 | M2: =VLOOKUP($A2,Form_Responses[],20,FALSE) -> 5 | N2: =VLOOKUP($A2,Form_Responses[],21,FALSE) -> 3 | O2: =VLOOKUP($A2,Form_Responses8[],4,FALSE) -> 6 | P2: =VLOOKUP($A2,Form_Responses8[],5,FALSE) -> 5 | Q2: =VLOOKUP($A2,Form_Responses8[],6,FALSE) -> 3 | R2: =VLOOKUP($A2,Form_Responses8[],7,FALSE) -> 4 | S2: =VLOOKUP($A2,Form_Responses8[],8,FALSE) -> 4 | T2: =VLOOKUP($A2,Form_Responses6[],4,FALSE) -> 6 | U2: =VLOOKUP($A2,Form_Responses6[],5,FALSE) -> 5 | V2: =VLOOKUP($A2,Form_Responses6[],6,FALSE) -> 5 | W2: =VLOOKUP($A2,Form_Responses6[],7,FALSE) -> 5 | X2: =VLOOKUP($A2,Form_Responses6[],8,FALSE) -> 4
A3: ='Task 1'!A49 -> 67c3 | B3: =VLOOKUP('CSV Results'!A3,'Task 1'!$A$48:$B$59,2,FALSE) -> B | C3: =VLOOKUP(A3,'Task 1'!A$74:B$85,2,FALSE) -> None | D3: =VLOOKUP($A3,'Task 1'!$A$16:$V$27,19,FALSE) -> 0.14285714 | E3: =MINUTE(VLOOKUP($A3,'Task 1'!$A$16:$V$27,22,FALSE))+SECOND(VLOOKUP($A3,'Task 1'!$A$16:$V$27,22,FALSE))/60 -> 25 | F3: =VLOOKUP($A3,'Task 2'!$A$2:$J$12,10,FALSE) -> 0 | G3: =MINUTE(VLOOKUP($A3,'Task 2'!$A$2:$J$12,2,FALSE))+SECOND(VLOOKUP($A3,'Task 2'!$A$2:$J$12,2,FALSE))/60 -> 12 | H3: =VLOOKUP($A3,'Task 3'!$A$2:$J$12,10,FALSE) -> 0 | I3: =MINUTE(VLOOKUP($A3,'Task 3'!$A$2:$J$12,2,FALSE))+SECOND(VLOOKUP($A3,'Task 3'!$A$2:$J$12,2,FALSE))/60 -> 12 | J3: =VLOOKUP($A3,Form_Responses[],17,FALSE) -> 3 | K3: =VLOOKUP($A3,Form_Responses[],18,FALSE) -> 6 | L3: =VLOOKUP($A3,Form_Responses[],19,FALSE) -> 6 | M3: =VLOOKUP($A3,Form_Responses[],20,FALSE) -> 5 | N3: =VLOOKUP($A3,Form_Responses[],21,FALSE) -> 4 | O3: =VLOOKUP($A3,Form_Responses8[],4,FALSE) -> 5 | P3: =VLOOKUP($A3,Form_Responses8[],5,FALSE) -> 7 | Q3: =VLOOKUP($A3,Form_Responses8[],6,FALSE) -> 7 | R3: =VLOOKUP($A3,Form_Responses8[],7,FALSE) -> 6 | S3: =VLOOKUP($A3,Form_Responses8[],8,FALSE) -> 7 | T3: =VLOOKUP($A3,Form_Responses6[],4,FALSE) -> 5 | U3: =VLOOKUP($A3,Form_Responses6[],5,FALSE) -> 7 | V3: =VLOOKUP($A3,Form_Responses6[],6,FALSE) -> 4 | W3: =VLOOKUP($A3,Form_Responses6[],7,FALSE) -> 6 | X3: =VLOOKUP($A3,Form_Responses6[],8,FALSE) -> 5
A4: ='Task 1'!A50 -> 0078 | B4: =VLOOKUP('CSV Results'!A4,'Task 1'!$A$48:$B$59,2,FALSE) -> A | C4: =VLOOKUP(A4,'Task 1'!A$74:B$85,2,FALSE) -> None | D4: =VLOOKUP($A4,'Task 1'!$A$16:$V$27,19,FALSE) -> 0.6547619 | E4: =MINUTE(VLOOKUP($A4,'Task 1'!$A$16:$V$27,22,FALSE))+SECOND(VLOOKUP($A4,'Task 1'!$A$16:$V$27,22,FALSE))/60 -> 25 | F4: =VLOOKUP($A4,'Task 2'!$A$2:$J$12,10,FALSE) -> 0 | G4: =MINUTE(VLOOKUP($A4,'Task 2'!$A$2:$J$12,2,FALSE))+SECOND(VLOOKUP($A4,'Task 2'!$A$2:$J$12,2,FALSE))/60 -> 12 | H4: =VLOOKUP($A4,'Task 3'!$A$2:$J$12,10,FALSE) -> 1 | I4: =MINUTE(VLOOKUP($A4,'Task 3'!$A$2:$J$12,2,FALSE))+SECOND(VLOOKUP($A4,'Task 3'!$A$2:$J$12,2,FALSE))/60 -> 12 | J4: =VLOOKUP($A4,Form_Responses[],17,FALSE) -> 4 | K4: =VLOOKUP($A4,Form_Responses[],18,FALSE) -> 4 | L4: =VLOOKUP($A4,Form_Responses[],19,FALSE) -> 3 | M4: =VLOOKUP($A4,Form_Responses[],20,FALSE) -> 4 | N4: =VLOOKUP($A4,Form_Responses[],21,FALSE) -> 3 | O4: =VLOOKUP($A4,Form_Responses8[],4,FALSE) -> 3 | P4: =VLOOKUP($A4,Form_Responses8[],5,FALSE) -> 2 | Q4: =VLOOKUP($A4,Form_Responses8[],6,FALSE) -> 4 | R4: =VLOOKUP($A4,Form_Responses8[],7,FALSE) -> 3 | S4: =VLOOKUP($A4,Form_Responses8[],8,FALSE) -> 2 | T4: =VLOOKUP($A4,Form_Responses6[],4,FALSE) -> 4 | U4: =VLOOKUP($A4,Form_Responses6[],5,FALSE) -> 3 | V4: =VLOOKUP($A4,Form_Responses6[],6,FALSE) -> 5 | W4: =VLOOKUP($A4,Form_Responses6[],7,FALSE) -> 4 | X4: =VLOOKUP($A4,Form_Responses6[],8,FALSE) -> 4
A5: ='Task 1'!A51 -> 1d20 | B5: =VLOOKUP('CSV Results'!A5,'Task 1'!$A$48:$B$59,2,FALSE) -> A | C5: =VLOOKUP(A5,'Task 1'!A$74:B$85,2,FALSE) -> Moderate | D5: =VLOOKUP($A5,'Task 1'!$A$16:$V$27,19,FALSE) -> 0.8452381 | E5: =MINUTE(VLOOKUP($A5,'Task 1'!$A$16:$V$27,22,FALSE))+SECOND(VLOOKUP($A5,'Task 1'!$A$16:$V$27,22,FALSE))/60 -> 24.5 | F5: =VLOOKUP($A5,'Task 2'!$A$2:$J$12,10,FALSE) -> 1 | G5: =MINUTE(VLOOKUP($A5,'Task 2'!$A$2:$J$12,2,FALSE))+SECOND(VLOOKUP($A5,'Task 2'!$A$2:$J$12,2,FALSE))/60 -> 12 | H5: =VLOOKUP($A5,'Task 3'!$A$2:$J$12,10,FALSE) -> 1 | I5: =MINUTE(VLOOKUP($A5,'Task 3'!$A$2:$J$12,2,FALSE))+SECOND(VLOOKUP($A5,'Task 3'!$A$2:$J$12,2,FALSE))/60 -> 7 | J5: =VLOOKUP($A5,Form_Responses[],17,FALSE) -> 6 | K5: =VLOOKUP($A5,Form_Responses[],18,FALSE) -> 5 | L5: =VLOOKUP($A5,Form_Responses[],19,FALSE) -> 2 | M5: =VLOOKUP($A5,Form_Responses[],20,FALSE) -> 5 | N5: =VLOOKUP($A5,Form_Responses[],21,FALSE) -> 1 | O5: =VLOOKUP($A5,Form_Responses8[],4,FALSE) -> 6 | P5: =VLOOKUP($A5,Form_Responses8[],5,FALSE) -> 7 | Q5: =VLOOKUP($A5,Form_Responses8[],6,FALSE) -> 2 | R5: =VLOOKUP($A5,Form_Responses8[],7,FALSE) -> 6 | S5: =VLOOKUP($A5,Form_Responses8[],8,FALSE) -> 1 | T5: =VLOOKUP($A5,Form_Responses6[],4,FALSE) -> 4 | U5: =VLOOKUP($A5,Form_Responses6[],5,FALSE) -> 2 | V5: =VLOOKUP($A5,Form_Responses6[],6,FALSE) -> 1 | W5: =VLOOKUP($A5,Form_Responses6[],7,FALSE) -> 2 | X5: =VLOOKUP($A5,Form_Responses6[],8,FALSE) -> 1
A6: ='Task 1'!A52 -> 33c6 | B6: =VLOOKUP('CSV Results'!A6,'Task 1'!$A$48:$B$59,2,FALSE) -> A | C6: =VLOOKUP(A6,'Task 1'!A$74:B$85,2,FALSE) -> Advanced | D6: =VLOOKUP($A6,'Task 1'!$A$16:$V$27,19,FALSE) -> 0.88095238 | E6: =MINUTE(VLOOKUP($A6,'Task 1'!$A$16:$V$27,22,FALSE))+SECOND(VLOOKUP($A6,'Task 1'!$A$16:$V$27,22,FALSE))/60 -> 25 | F6: =VLOOKUP($A6,'Task 2'!$A$2:$J$12,10,FALSE) -> 1 | G6: =MINUTE(VLOOKUP($A6,'Task 2'!$A$2:$J$12,2,FALSE))+SECOND(VLOOKUP($A6,'Task 2'!$A$2:$J$12,2,FALSE))/60 -> 9 | H6: =VLOOKUP($A6,'Task 3'!$A$2:$J$12,10,FALSE) -> 1 | I6: =MINUTE(VLOOKUP($A6,'Task 3'!$A$2:$J$12,2,FALSE))+SECOND(VLOOKUP($A6,'Task 3'!$A$2:$J$12,2,FALSE))/60 -> 12 | J6: =VLOOKUP($A6,Form_Responses[],17,FALSE) -> 4 | K6: =VLOOKUP($A6,Form_Responses[],18,FALSE) -> 5 | L6: =VLOOKUP($A6,Form_Responses[],19,FALSE) -> 1 | M6: =VLOOKUP($A6,Form_Responses[],20,FALSE) -> 3 | N6: =VLOOKUP($A6,Form_Responses[],21,FALSE) -> 1 | O6: =VLOOKUP($A6,Form_Responses8[],4,FALSE) -> 4 | P6: =VLOOKUP($A6,Form_Responses8[],5,FALSE) -> 2 | Q6: =VLOOKUP($A6,Form_Responses8[],6,FALSE) -> 2 | R6: =VLOOKUP($A6,Form_Responses8[],7,FALSE) -> 2 | S6: =VLOOKUP($A6,Form_Responses8[],8,FALSE) -> 1 | T6: =VLOOKUP($A6,Form_Responses6[],4,FALSE) -> 5 | U6: =VLOOKUP($A6,Form_Responses6[],5,FALSE) -> 5 | V6: =VLOOKUP($A6,Form_Responses6[],6,FALSE) -> 3 | W6: =VLOOKUP($A6,Form_Responses6[],7,FALSE) -> 5 | X6: =VLOOKUP($A6,Form_Responses6[],8,FALSE) -> 2
A7: ='Task 1'!A53 -> 49f7 | B7: =VLOOKUP('CSV Results'!A7,'Task 1'!$A$48:$B$59,2,FALSE) -> B | C7: =VLOOKUP(A7,'Task 1'!A$74:B$85,2,FALSE) -> Basic | D7: =VLOOKUP($A7,'Task 1'!$A$16:$V$27,19,FALSE) -> 0.79761905 | E7: =MINUTE(VLOOKUP($A7,'Task 1'!$A$16:$V$27,22,FALSE))+SECOND(VLOOKUP($A7,'Task 1'!$A$16:$V$27,22,FALSE))/60 -> 24 | F7: =VLOOKUP($A7,'Task 2'!$A$2:$J$12,10,FALSE) -> 0 | G7: =MINUTE(VLOOKUP($A7,'Task 2'!$A$2:$J$12,2,FALSE))+SECOND(VLOOKUP($A7,'Task 2'!$A$2:$J$12,2,FALSE))/60 -> 12 | H7: =VLOOKUP($A7,'Task 3'!$A$2:$J$12,10,FALSE) -> 1 | I7: =MINUTE(VLOOKUP($A7,'Task 3'!$A$2:$J$12,2,FALSE))+SECOND(VLOOKUP($A7,'Task 3'!$A$2:$J$12,2,FALSE))/60 -> 12 | J7: =VLOOKUP($A7,Form_Responses[],17,FALSE) -> 6 | K7: =VLOOKUP($A7,Form_Responses[],18,FALSE) -> 5 | L7: =VLOOKUP($A7,Form_Responses[],19,FALSE) -> 2 | M7: =VLOOKUP($A7,Form_Responses[],20,FALSE) -> 6 | N7: =VLOOKUP($A7,Form_Responses[],21,FALSE) -> 5 | O7: =VLOOKUP($A7,Form_Responses8[],4,FALSE) -> 7 | P7: =VLOOKUP($A7,Form_Responses8[],5,FALSE) -> 6 | Q7: =VLOOKUP($A7,Form_Responses8[],6,FALSE) -> 5 | R7: =VLOOKUP($A7,Form_Responses8[],7,FALSE) -> 6 | S7: =VLOOKUP($A7,Form_Responses8[],8,FALSE) -> 7 | T7: =VLOOKUP($A7,Form_Responses6[],4,FALSE) -> 7 | U7: =VLOOKUP($A7,Form_Responses6[],5,FALSE) -> 7 | V7: =VLOOKUP($A7,Form_Responses6[],6,FALSE) -> 5 | W7: =VLOOKUP($A7,Form_Responses6[],7,FALSE) -> 6 | X7: =VLOOKUP($A7,Form_Responses6[],8,FALSE) -> 5
A8: ='Task 1'!A54 -> 536e | B8: =VLOOKUP('CSV Results'!A8,'Task 1'!$A$48:$B$59,2,FALSE) -> A | C8: =VLOOKUP(A8,'Task 1'!A$74:B$85,2,FALSE) -> None | D8: =VLOOKUP($A8,'Task 1'!$A$16:$V$27,19,FALSE) -> 0.26190476 | E8: =MINUTE(VLOOKUP($A8,'Task 1'!$A$16:$V$27,22,FALSE))+SECOND(VLOOKUP($A8,'Task 1'!$A$16:$V$27,22,FALSE))/60 -> 25 | F8: =VLOOKUP($A8,'Task 2'!$A$2:$J$12,10,FALSE) -> 0 | G8: =MINUTE(VLOOKUP($A8,'Task 2'!$A$2:$J$12,2,FALSE))+SECOND(VLOOKUP($A8,'Task 2'!$A$2:$J$12,2,FALSE))/60 -> 12 | H8: =VLOOKUP($A8,'Task 3'!$A$2:$J$12,10,FALSE) -> 0 | I8: =MINUTE(VLOOKUP($A8,'Task 3'!$A$2:$J$12,2,FALSE))+SECOND(VLOOKUP($A8,'Task 3'!$A$2:$J$12,2,FALSE))/60 -> 12 | J8: =VLOOKUP($A8,Form_Responses[],17,FALSE) -> 4 | K8: =VLOOKUP($A8,Form_Responses[],18,FALSE) -> 4 | L8: =VLOOKUP($A8,Form_Responses[],19,FALSE) -> 3 | M8: =VLOOKUP($A8,Form_Responses[],20,FALSE) -> 4 | N8: =VLOOKUP($A8,Form_Responses[],21,FALSE) -> 2 | O8: =VLOOKUP($A8,Form_Responses8[],4,FALSE) -> 6 | P8: =VLOOKUP($A8,Form_Responses8[],5,FALSE) -> 6 | Q8: =VLOOKUP($A8,Form_Responses8[],6,FALSE) -> 2 | R8: =VLOOKUP($A8,Form_Responses8[],7,FALSE) -> 6 | S8: =VLOOKUP($A8,Form_Responses8[],8,FALSE) -> 5 | T8: =VLOOKUP($A8,Form_Responses6[],4,FALSE) -> 6 | U8: =VLOOKUP($A8,Form_Responses6[],5,FALSE) -> 6 | V8: =VLOOKUP($A8,Form_Responses6[],6,FALSE) -> 2 | W8: =VLOOKUP($A8,Form_Responses6[],7,FALSE) -> 6 | X8: =VLOOKUP($A8,Form_Responses6[],8,FALSE) -> 6
A9: ='Task 1'!A55 -> 5694 | B9: =VLOOKUP('CSV Results'!A9,'Task 1'!$A$48:$B$59,2,FALSE) -> B | C9: =VLOOKUP(A9,'Task 1'!A$74:B$85,2,FALSE) -> None | D9: =VLOOKUP($A9,'Task 1'!$A$16:$V$27,19,FALSE) -> 0.42857143 | E9: =MINUTE(VLOOKUP($A9,'Task 1'!$A$16:$V$27,22,FALSE))+SECOND(VLOOKUP($A9,'Task 1'!$A$16:$V$27,22,FALSE))/60 -> 25 | F9: =VLOOKUP($A9,'Task 2'!$A$2:$J$12,10,FALSE) -> 0 | G9: =MINUTE(VLOOKUP($A9,'Task 2'!$A$2:$J$12,2,FALSE))+SECOND(VLOOKUP($A9,'Task 2'!$A$2:$J$12,2,FALSE))/60 -> 12 | H9: =VLOOKUP($A9,'Task 3'!$A$2:$J$12,10,FALSE) -> 0 | I9: =MINUTE(VLOOKUP($A9,'Task 3'!$A$2:$J$12,2,FALSE))+SECOND(VLOOKUP($A9,'Task 3'!$A$2:$J$12,2,FALSE))/60 -> 12 | J9: =VLOOKUP($A9,Form_Responses[],17,FALSE) -> 6 | K9: =VLOOKUP($A9,Form_Responses[],18,FALSE) -> 7 | L9: =VLOOKUP($A9,Form_Responses[],19,FALSE) -> 6 | M9: =VLOOKUP($A9,Form_Responses[],20,FALSE) -> 5 | N9: =VLOOKUP($A9,Form_Responses[],21,FALSE) -> 5 | O9: =VLOOKUP($A9,Form_Responses8[],4,FALSE) -> 5 | P9: =VLOOKUP($A9,Form_Responses8[],5,FALSE) -> 7 | Q9: =VLOOKUP($A9,Form_Responses8[],6,FALSE) -> 6 | R9: =VLOOKUP($A9,Form_Responses8[],7,FALSE) -> 5 | S9: =VLOOKUP($A9,Form_Responses8[],8,FALSE) -> 7 | T9: =VLOOKUP($A9,Form_Responses6[],4,FALSE) -> 5 | U9: =VLOOKUP($A9,Form_Responses6[],5,FALSE) -> 6 | V9: =VLOOKUP($A9,Form_Responses6[],6,FALSE) -> 6 | W9: =VLOOKUP($A9,Form_Responses6[],7,FALSE) -> 6 | X9: =VLOOKUP($A9,Form_Responses6[],8,FALSE) -> 6
A10: ='Task 1'!A56 -> bdb6 | B10: =VLOOKUP('CSV Results'!A10,'Task 1'!$A$48:$B$59,2,FALSE) -> B | C10: =VLOOKUP(A10,'Task 1'!A$74:B$85,2,FALSE) -> Advanced | D10: =VLOOKUP($A10,'Task 1'!$A$16:$V$27,19,FALSE) -> 0.75 | E10: =MINUTE(VLOOKUP($A10,'Task 1'!$A$16:$V$27,22,FALSE))+SECOND(VLOOKUP($A10,'Task 1'!$A$16:$V$27,22,FALSE))/60 -> 17 | F10: =VLOOKUP($A10,'Task 2'!$A$2:$J$12,10,FALSE) -> 0 | G10: =MINUTE(VLOOKUP($A10,'Task 2'!$A$2:$J$12,2,FALSE))+SECOND(VLOOKUP($A10,'Task 2'!$A$2:$J$12,2,FALSE))/60 -> 9.5 | H10: =VLOOKUP($A10,'Task 3'!$A$2:$J$12,10,FALSE) -> 0 | I10: =MINUTE(VLOOKUP($A10,'Task 3'!$A$2:$J$12,2,FALSE))+SECOND(VLOOKUP($A10,'Task 3'!$A$2:$J$12,2,FALSE))/60 -> 10 | J10: =VLOOKUP($A10,Form_Responses[],17,FALSE) -> 3 | K10: =VLOOKUP($A10,Form_Responses[],18,FALSE) -> 2 | L10: =VLOOKUP($A10,Form_Responses[],19,FALSE) -> 6 | M10: =VLOOKUP($A10,Form_Responses[],20,FALSE) -> 4 | N10: =VLOOKUP($A10,Form_Responses[],21,FALSE) -> 2 | O10: =VLOOKUP($A10,Form_Responses8[],4,FALSE) -> 6 | P10: =VLOOKUP($A10,Form_Responses8[],5,FALSE) -> 5 | Q10: =VLOOKUP($A10,Form_Responses8[],6,FALSE) -> 3 | R10: =VLOOKUP($A10,Form_Responses8[],7,FALSE) -> 4 | S10: =VLOOKUP($A10,Form_Responses8[],8,FALSE) -> 3 | T10: =VLOOKUP($A10,Form_Responses6[],4,FALSE) -> 6 | U10: =VLOOKUP($A10,Form_Responses6[],5,FALSE) -> 5 | V10: =VLOOKUP($A10,Form_Responses6[],6,FALSE) -> 3 | W10: =VLOOKUP($A10,Form_Responses6[],7,FALSE) -> 5 | X10: =VLOOKUP($A10,Form_Responses6[],8,FALSE) -> 4
A11: ='Task 1'!A57 -> bdf7 | B11: =VLOOKUP('CSV Results'!A11,'Task 1'!$A$48:$B$59,2,FALSE) -> A | C11: =VLOOKUP(A11,'Task 1'!A$74:B$85,2,FALSE) -> Basic | D11: =VLOOKUP($A11,'Task 1'!$A$16:$V$27,19,FALSE) -> 0.21428571 | E11: =MINUTE(VLOOKUP($A11,'Task 1'!$A$16:$V$27,22,FALSE))+SECOND(VLOOKUP($A11,'Task 1'!$A$16:$V$27,22,FALSE))/60 -> 25 | F11: =VLOOKUP($A11,'Task 2'!$A$2:$J$12,10,FALSE) -> 1 | G11: =MINUTE(VLOOKUP($A11,'Task 2'!$A$2:$J$12,2,FALSE))+SECOND(VLOOKUP($A11,'Task 2'!$A$2:$J$12,2,FALSE))/60 -> 9 | H11: =VLOOKUP($A11,'Task 3'!$A$2:$J$12,10,FALSE) -> 0 | I11: =MINUTE(VLOOKUP($A11,'Task 3'!$A$2:$J$12,2,FALSE))+SECOND(VLOOKUP($A11,'Task 3'!$A$2:$J$12,2,FALSE))/60 -> 5 | J11: =VLOOKUP($A11,Form_Responses[],17,FALSE) -> 5 | K11: =VLOOKUP($A11,Form_Responses[],18,FALSE) -> 6 | L11: =VLOOKUP($A11,Form_Responses[],19,FALSE) -> 3 | M11: =VLOOKUP($A11,Form_Responses[],20,FALSE) -> 3 | N11: =VLOOKUP($A11,Form_Responses[],21,FALSE) -> 5 | O11: =VLOOKUP($A11,Form_Responses8[],4,FALSE) -> 3 | P11: =VLOOKUP($A11,Form_Responses8[],5,FALSE) -> 3 | Q11: =VLOOKUP($A11,Form_Responses8[],6,FALSE) -> 4 | R11: =VLOOKUP($A11,Form_Responses8[],7,FALSE) -> 3 | S11: =VLOOKUP($A11,Form_Responses8[],8,FALSE) -> 2 | T11: =VLOOKUP($A11,Form_Responses6[],4,FALSE) -> 2 | U11: =VLOOKUP($A11,Form_Responses6[],5,FALSE) -> 2 | V11: =VLOOKUP($A11,Form_Responses6[],6,FALSE) -> 4 | W11: =VLOOKUP($A11,Form_Responses6[],7,FALSE) -> 3 | X11: =VLOOKUP($A11,Form_Responses6[],8,FALSE) -> 2
A12: ='Task 1'!A58 -> 18e7 | B12: =VLOOKUP('CSV Results'!A12,'Task 1'!$A$48:$B$59,2,FALSE) -> A | C12: =VLOOKUP(A12,'Task 1'!A$74:B$85,2,FALSE) -> Advanced | D12: =VLOOKUP($A12,'Task 1'!$A$16:$V$27,19,FALSE) -> 0.69047619 | E12: =MINUTE(VLOOKUP($A12,'Task 1'!$A$16:$V$27,22,FALSE))+SECOND(VLOOKUP($A12,'Task 1'!$A$16:$V$27,22,FALSE))/60 -> 24.5 | F12: =VLOOKUP($A12,'Task 2'!$A$2:$J$12,10,FALSE) -> #N/A | G12: =MINUTE(VLOOKUP($A12,'Task 2'!$A$2:$J$12,2,FALSE))+SECOND(VLOOKUP($A12,'Task 2'!$A$2:$J$12,2,FALSE))/60 -> #N/A | H12: =VLOOKUP($A12,'Task 3'!$A$2:$J$12,10,FALSE) -> #N/A | I12: =MINUTE(VLOOKUP($A12,'Task 3'!$A$2:$J$12,2,FALSE))+SECOND(VLOOKUP($A12,'Task 3'!$A$2:$J$12,2,FALSE))/60 -> #N/A | J12: =VLOOKUP($A12,Form_Responses[],17,FALSE) -> 4 | K12: =VLOOKUP($A12,Form_Responses[],18,FALSE) -> 4 | L12: =VLOOKUP($A12,Form_Responses[],19,FALSE) -> 2 | M12: =VLOOKUP($A12,Form_Responses[],20,FALSE) -> 2 | N12: =VLOOKUP($A12,Form_Responses[],21,FALSE) -> 1 | O12: =VLOOKUP($A12,Form_Responses8[],4,FALSE) -> #N/A | P12: =VLOOKUP($A12,Form_Responses8[],5,FALSE) -> #N/A | Q12: =VLOOKUP($A12,Form_Responses8[],6,FALSE) -> #N/A | R12: =VLOOKUP($A12,Form_Responses8[],7,FALSE) -> #N/A | S12: =VLOOKUP($A12,Form_Responses8[],8,FALSE) -> #N/A | T12: =VLOOKUP($A12,Form_Responses6[],4,FALSE) -> #N/A | U12: =VLOOKUP($A12,Form_Responses6[],5,FALSE) -> #N/A | V12: =VLOOKUP($A12,Form_Responses6[],6,FALSE) -> #N/A | W12: =VLOOKUP($A12,Form_Responses6[],7,FALSE) -> #N/A | X12: =VLOOKUP($A12,Form_Responses6[],8,FALSE) -> #N/A
A13: ='Task 1'!A59 -> e43c | B13: =VLOOKUP('CSV Results'!A13,'Task 1'!$A$48:$B$59,2,FALSE) -> B | C13: =VLOOKUP(A13,'Task 1'!A$74:B$85,2,FALSE) -> Moderate | D13: =VLOOKUP($A13,'Task 1'!$A$16:$V$27,19,FALSE) -> 0.66666667 | E13: =MINUTE(VLOOKUP($A13,'Task 1'!$A$16:$V$27,22,FALSE))+SECOND(VLOOKUP($A13,'Task 1'!$A$16:$V$27,22,FALSE))/60 -> 22.5 | F13: =VLOOKUP($A13,'Task 2'!$A$2:$J$12,10,FALSE) -> 1 | G13: =MINUTE(VLOOKUP($A13,'Task 2'!$A$2:$J$12,2,FALSE))+SECOND(VLOOKUP($A13,'Task 2'!$A$2:$J$12,2,FALSE))/60 -> 9 | H13: =VLOOKUP($A13,'Task 3'!$A$2:$J$12,10,FALSE) -> 0 | I13: =MINUTE(VLOOKUP($A13,'Task 3'!$A$2:$J$12,2,FALSE))+SECOND(VLOOKUP($A13,'Task 3'!$A$2:$J$12,2,FALSE))/60 -> 7 | J13: =VLOOKUP($A13,Form_Responses[],17,FALSE) -> 7 | K13: =VLOOKUP($A13,Form_Responses[],18,FALSE) -> 5 | L13: =VLOOKUP($A13,Form_Responses[],19,FALSE) -> 3 | M13: =VLOOKUP($A13,Form_Responses[],20,FALSE) -> 5 | N13: =VLOOKUP($A13,Form_Responses[],21,FALSE) -> 7 | O13: =VLOOKUP($A13,Form_Responses8[],4,FALSE) -> 7 | P13: =VLOOKUP($A13,Form_Responses8[],5,FALSE) -> 7 | Q13: =VLOOKUP($A13,Form_Responses8[],6,FALSE) -> 4 | R13: =VLOOKUP($A13,Form_Responses8[],7,FALSE) -> 7 | S13: =VLOOKUP($A13,Form_Responses8[],8,FALSE) -> 6 | T13: =VLOOKUP($A13,Form_Responses6[],4,FALSE) -> 5 | U13: =VLOOKUP($A13,Form_Responses6[],5,FALSE) -> 4 | V13: =VLOOKUP($A13,Form_Responses6[],6,FALSE) -> 1 | W13: =VLOOKUP($A13,Form_Responses6[],7,FALSE) -> 5 | X13: =VLOOKUP($A13,Form_Responses6[],8,FALSE) -> 3

Sheet Task 1
A1: Participant Key | B1: Completion Time | C1: What is the primary goal of the agent? | D1: Did the agent complete its task? | E1: What are the main action categories performed by the agent? | F1: What is the most frequently performed action? | G1: What is the key challenge or issue the agent encounters during the task? | H1: Does the agent exhibit any repetitive behavior? If so, describe one example. | I1: What specific changes does the agent make to the cli.py file when it first modifies it? | J1: Which specific files does the agent modify to implement the income report generation feature? | K1: What feedback does the agent receive after its first attempt to run the test script for the finance tracker, and how does it influence the next action? | L1: Which Python packages does the agent install over the course of the run? | M1: What feedback does the agent receive from running the test script for the finance tracker after it has solved all import issues? | N1: Which file is the agent primarily focused on modifying towards the end of the run? | O1: Does the agent ever attempt to make the same change twice before reevaluating the tests? If so, describe one instance. | P1: Analyze the final four changes the agent makes to the repository. How do these changes relate to each other? | Q1: Mental Demand | R1: Temporal Demand | S1: Performance | T1: Effort | U1: Frustration
A2: 5694 | B2: 0.017361111 | C2: Enhance the `finance_tracker` project by adding income tracking functionality to complement the existing expense, budget, user, and reporting features. The feature allows users to record income sources, track income by category and date, calculate net balance, and integrate with reporting and CLI. | D2: No, the task was not completed. | E2: Observations, replacements, package installation | F2: Observations | G2: FunctionCallingFormatError | H2: The Agent requeries the model 3 times in a row after a FunctionCallingFormatError | I2: - `add_income <amount> <category> <description> [tags] [recurring] [period]` - `generate_income_report [start_date] [end_date]` | J2: cli.py, README.md | K2: ModuleNotFoundError> No module named 'pandas' | L2: matplotlib, pandas | M2: IndentationError | N2: cli.py | P2: The Agent compares two different versions of the cli.py file | Q2: 6 | R2: 7 | S2: 6 | T2: 5 | U2: 5
A3: 0078 | B3: 0.017361111 | C3: The agents goal is to implement an income tracking feature to a python project with cli functionality and integrating it into the rest of the program. | D3: Yes, the task was completed successfully. | E3: Adding functionality of income tracking and integrating it into the CLI | F3: adding the income report generation to the cli | G3: The agent seems to have troubles with python syntax, i.e., the indentation (IndentationError) | H3: Yes, it does. It requests multiple times to “Create the 'IncomeTracker' class ... to satisfy the PR description", the commit titles also indicate this with multiple "Add income report generation to CLI" | I3: import cmd 2 import argparse 3 from finance_tracker.expenses import ExpenseTracker 4 from finance_tracker.budgets import BudgetManager 5 from finance_tracker.users import UserManager 6 from finance_tracker.reports import FinancialReport 7 from finance_tracker.income import IncomeTracker 8 from datetime import datetime 9 10 class FinanceTrackerCLI(cmd.Cmd): 11 """Command-line interface for the finance tracker.""" 12 prompt = "FinanceTracker> " 13 intro = "Welcome to the Personal Finance Tracker. Type 'help' for commands." 14 15 def __init__(self): 16 super().__init__() 17 self.user_manager = UserManager() 18 self.current_user = None 19 self.expense_tracker = None 20 self.budget_manager = None 21 self.report_generator = None 22 23 def do_login(self, arg): 24 """Login to the system: login <username> <password>""" 25 args = arg.split() 26 if len(args) != 2: 27 print("Usage: login <username> <password>") 28 return 29 username, password = args 30 if self.user_manager.authenticate_user(username, password): 31 self.current_user = username 32 self.expense_tracker = ExpenseTracker(username) 33 self.budget_manager = BudgetManager(username) 34 self.report_generator = FinancialReport(username, self.expense_tracker, self.budget_manager) 35 print(f"Logged in as {username}") 36 else: 37 print("Invalid username or password") 38 39 def do_register(self, arg): 40 """Register a new user: register <username> <password> <email>""" 41 args = arg.split() 42 if len(args) != 3: 43 print("Usage: register <username> <password> <email>") 44 return 45 try: 46 self.user_manager.register_user(*args) 47 print(f"User {args[0]} registered successfully") 48 except ValueError as e: 49 print(f"Error: {e}") 50 51 def do_add_expense(self, arg): 52 """Add an expense: add_expense <amount> <category> <description> [tags] [recurring] [period]""" 53 if not self.current_user: 54 print("Please login first") 55 return 56 args = arg.split() 57 if len(args) < 3: 58 print("Usage: add_expense <amount> <category> <description> [tags] [recurring] [period]") 59 return 60 amount, category, description = args[:3] 61 tags = args[3].split(",") if len(args) > 3 else [] 62 is_recurring = args[4].lower() == "true" if len(args) > 4 else False 63 period = args[5] if len(args) > 5 else None 64 try: 65 expense_id = self.expense_tracker.add_expense(float(amount), category, description, 66 tags=tags, is_recurring=is_recurring, 67 recurrence_period=period) 68 print(f"Expense added with ID: {expense_id}") 69 except ValueError as e: 70 print(f"Error: {e}") 71 72 def do_set_budget(self, arg): 73 """Set a budget: set_budget <category> <amount> [period] [alert_threshold]""" 74 if not self.current_user: 75 print("Please login first") 76 return 77 args = arg.split() 78 if len(args) < 2: 79 print("Usage: set_budget <category> <amount> [period] [alert_threshold]") 80 return 81 category, amount = args[:2] 82 period = args[2] if len(args) > 2 else "monthly" 83 alert_threshold = float(args[3]) if len(args) > 3 else 0.8 84 try: 85 self.budget_manager.set_budget(category, float(amount), period, alert_threshold) 86 print(f"Budget set for {category} ({period})") 87 except ValueError as e: 88 print(f"Error: {e}") 89 90 def do_generate_report(self, arg): 91 """Generate a report: generate_report <type> [start_date] [end_date]""" 92 if not self.current_user: 93 print("Please login first") 94 return 95 args = arg.split() 96 if len(args) < 1: 97 print("Usage: generate_report <type> [start_date] [end_date]") 98 return 99 report_type = args[0] 100 start_date = args[1] if len(args) > 1 else None 101 end_date = args[2] if len(args) > 2 else None 102 try: 103 report_file = self.report_generator.generate_report_pdf(report_type, start_date, end_date) 104 print(f"Report generated: {report_file}") 105 except Exception as e: 106 print(f"Error: {e}") 107 108 def do_exit(self, arg): 109 """Exit the CLI.""" 110 print("Goodbye!") 111 return True 112 113 def preloop(self): 114 """Initialize CLI state.""" 115 print("Personal Finance Tracker CLI. Type 'register' or 'login' to begin.") | J3: cli.py, report.py, income.py | K3: Error (ModuleNotFoundError: No module named 'pandas'); next the agent asks the LLM what to do, the LLM suggests to install pandas with pip | L3: pandas and matplotlib | M3: An indentation error | N3: cli.py | P3: first test, then error so next "updated logic" | Q3: 4 | R3: 4 | S3: 3 | T3: 4 | U3: 3
A4: 18e7 | B4: 0.017013889 | C4: The agent goal is to implement new feature or new function-ality- that was described in the PR specifically the income tracking feature for a finance tracker project. | D4: Yes, the task was completed successfully. | E4: File editing, File listing, Executing commands such as execute script and install package | F4: File editing | G4: Correctly editing the file? as there are many indentation errors… | H4: Yes there was some repetition, e.g, repeated listing of files at the start | I4: 1 import cmd 2 import argparse 3 from finance_tracker.expenses import ExpenseTracker 4 from finance_tracker.budgets import BudgetManager 5 from finance_tracker.users import UserManager 6 from finance_tracker.reports import FinancialReport 7 from finance_tracker.income import IncomeTracker 8 from datetime import datetime 9 10 class FinanceTrackerCLI(cmd.Cmd): 11 """Command-line interface for the finance tracker.""" 12 prompt = "FinanceTracker> " 13 intro = "Welcome to the Personal Finance Tracker. Type 'help' for commands." 14 15 def __init__(self): 16 super().__init__() 17 self.user_manager = UserManager() 18 self.current_user = None 19 self.expense_tracker = None 20 self.budget_manager = None 21 self.report_generator = None 22 23 def do_login(self, arg): 24 """Login to the system: login <username> <password>""" 25 args = arg.split() 26 if len(args) != 2: 27 print("Usage: login <username> <password>") 28 return 29 username, password = args 30 if self.user_manager.authenticate_user(username, password): 31 self.current_user = username 32 self.expense_tracker = ExpenseTracker(username) 33 self.budget_manager = BudgetManager(username) 34 self.report_generator = FinancialReport(username, self.expense_tracker, self.budget_manager) 35 print(f"Logged in as {username}") 36 else: 37 print("Invalid username or password") 38 39 def do_register(self, arg): 40 """Register a new user: register <username> <password> <email>""" 41 args = arg.split() 42 if len(args) != 3: 43 print("Usage: register <username> <password> <email>") 44 return 45 try: 46 self.user_manager.register_user(*args) 47 print(f"User {args[0]} registered successfully") 48 except ValueError as e: 49 print(f"Error: {e}") 50 51 def do_add_expense(self, arg): 52 """Add an expense: add_expense <amount> <category> <description> [tags] [recurring] [period]""" 53 if not self.current_user: 54 print("Please login first") 55 return 56 args = arg.split() 57 if len(args) < 3: 58 print("Usage: add_expense <amount> <category> <description> [tags] [recurring] [period]") 59 return 60 amount, category, description = args[:3] 61 tags = args[3].split(",") if len(args) > 3 else [] 62 is_recurring = args[4].lower() == "true" if len(args) > 4 else False 63 period = args[5] if len(args) > 5 else None 64 try: 65 expense_id = self.expense_tracker.add_expense(float(amount), category, description, 66 tags=tags, is_recurring=is_recurring, 67 recurrence_period=period) 68 print(f"Expense added with ID: {expense_id}") 69 except ValueError as e: 70 print(f"Error: {e}") 71 72 def do_set_budget(self, arg): 73 """Set a budget: set_budget <category> <amount> [period] [alert_threshold]""" 74 if not self.current_user: 75 print("Please login first") 76 return 77 args = arg.split() 78 if len(args) < 2: 79 print("Usage: set_budget <category> <amount> [period] [alert_threshold]") 80 return 81 category, amount = args[:2] 82 period = args[2] if len(args) > 2 else "monthly" 83 alert_threshold = float(args[3]) if len(args) > 3 else 0.8 84 try: 85 self.budget_manager.set_budget(category, float(amount), period, alert_threshold) 86 print(f"Budget set for {category} ({period})") 87 except ValueError as e: 88 print(f"Error: {e}") 89 90 def do_generate_report(self, arg): 91 """Generate a report: generate_report <type> [start_date] [end_date]""" 92 if not self.current_user: 93 print("Please login first") 94 return 95 args = arg.split() 96 if len(args) < 1: 97 print("Usage: generate_report <type> [start_date] [end_date]") 98 return 99 report_type = args[0] 100 start_date = args[1] if len(args) > 1 else None 101 end_date = args[2] if len(args) > 2 else None 102 try: 103 report_file = self.report_generator.generate_report_pdf(report_type, start_date, end_date) 104 print(f"Report generated: {report_file}") 105 except Exception as e: 106 print(f"Error: {e}") 107 108 def do_exit(self, arg): 109 """Exit the CLI.""" 110 print("Goodbye!") 111 return True 112 113 def preloop(self): 114 """Initialize CLI state.""" 115 print("Personal Finance Tracker CLI. Type 'register' or 'login' to begin.") | J4: income.py, expenses.py, reports.py, cli.py, README, | K4: Missing module pandas, the agent fixes it by installing the package | L4: pandas, matplotlib | M4: Error indicating indentation problems | N4: cli.py | O4: There is a replace old income report and old method generation before running tests but not sure if they count as same change twice. Otherwise No. | P4: From the diff comparison they look similar | Q4: 4 | R4: 4 | S4: 2 | T4: 2 | U4: 1
A5: 1d20 | B5: 0.017013889 | C5: The goal is to implement a new feature as described by a PR description | D5: No, the task was not completed. | E5: Listing contents of a directory, reading a file writing to a file, creating a new file, modifying a file via diff syntax, running bash commands | F5: Modifying the contents of a file | G5: The agent has trouble fixing a syntax error (the indentation error) | H5: The agent modified a part of the code that was not the erroneous part of the code. It tried multiple times to fix the indentation error by modifying a different part of the code. | I5: 7 + from finance_tracker.income import IncomeTracker | J5: income.py, expenses.py, reports.py, cli.py | K5: It gets the missing module error, and it tries to install the missing library | L5: pandas, matplotlib | M5: It encounters the indentation error | N5: cli.py | O5: str_replace_editor str_replace /finance_tracker/finance_tracker/cli.py --old_str ' def do_generate_income_report(self, arg):' --new_str ' def do_generate_income_report(self, arg):\n \"\"\"Generate an income report: generate_income_report [start_date] [end_date]\"\"\"\n if not self.current_user:\n print(\"Please login first\")\n return\n args = arg.split()\n start_date = args[0] if len(args) > 0 else None\n end_date = args[1] if len(args) > 1 else None\n try:\n report_data = self.income_tracker.generate_income_summary(start_date, end_date)\n print(json.dumps(report_data, indent=2))\n except Exception as e:\n print(f\"Error: {e}\")\n' | P5: They are all modifying the same location of the code, which is not the location that needs a fix. Their purpose is to fix the indentation error, but the edits are the same. | Q5: 6 | R5: 5 | S5: 2 | T5: 5 | U5: 1
A6: 33c6 | B6: 0.017361111 | C6: Implementing a feature as suggested by a pull request | D6: No, the task was not completed. | E6: listing files, showing file content, make modifications to files, create files, execute tests, install dependencies | F6: editing files | G6: Trying to add code to generate an income report. After multiple tries of making this change the tests always fail with an IndentationError. | H6: The agent adds the code for generating an income report 6 times in a row before execution ends. It is always the same code change. | I6: object {2} tool : str_replace_editor str_replace /finance_tracker/finance_tracker/cli.py --old_str 'from finance_tracker.reports import FinancialReport' --new_str 'from finance_tracker.reports import FinancialReport\nfrom finance_tracker.income import IncomeTracker' args : null | J6: cli.py, reports.py, expenses.py, income.py | K6: Traceback (most recent call last): File "/finance_tracker/finance_tracker/tests/test_income.py", line 5, in <module> from finance_tracker.reports import FinancialReport File "/finance_tracker/finance_tracker/reports.py", line 5, in <module> import pandas as pd ModuleNotFoundError: No module named 'pandas' The agent then installs the pandas dependency using pip | L6: pandas, matplotlib | M6: Traceback (most recent call last): File "/finance_tracker/finance_tracker/tests/test_income.py", line 7, in <module> from finance_tracker.cli import FinanceTrackerCLI File "/finance_tracker/finance_tracker/cli.py", line 41 def do_generate_income_report(self, arg): ^ IndentationError: expected an indented block after function definition on line 40 | N6: cli.py | O6: Yes. Tool call 1: object {2} tool : str_replace_editor str_replace /finance_tracker/finance_tracker/cli.py --old_str ' def do_generate_income_report(self, arg):' --new_str ' def do_generate_income_report(self, arg):\n \"\"\"Generate an income report: generate_income_report [start_date] [end_date]\"\"\"\n if not self.current_user:\n print(\"Please login first\")\n return\n args = arg.split()\n start_date = args[0] if len(args) > 0 else None\n end_date = args[1] if len(args) > 1 else None\n try:\n report_data = self.income_tracker.generate_income_summary(start_date, end_date)\n print(json.dumps(report_data, indent=2))\n except Exception as e:\n print(f\"Error: {e}\")\n' args : null Tool call 2: object {2} tool : str_replace_editor str_replace /finance_tracker/finance_tracker/cli.py --old_str ' def do_generate_income_report(self, arg):' --new_str ' def do_generate_income_report(self, arg):\n \"\"\"Generate an income report: generate_income_report [start_date] [end_date]\"\"\"\n if not self.current_user:\n print(\"Please login first\")\n return\n args = arg.split()\n start_date = args[0] if len(args) > 0 else None\n end_date = args[1] if len(args) > 1 else None\n try:\n report_data = self.income_tracker.generate_income_summary(start_date, end_date)\n print(json.dumps(report_data, indent=2))\n except Exception as e:\n print(f\"Error: {e}\")\n' args : null | P6: They are all making the same change to cli.py. | Q6: 4 | R6: 5 | S6: 1 | T6: 3 | U6: 1
A7: 49f7 | B7: 0.016666667 | C7: The agents goal is to add an income tracking feature to a personal finance tracker written in python | D7: No, the task was not completed. | E7: Listing directories (ls), printing file contents (cat), writing file contents (str_replace_editor), running program (python3) | F7: str_replace_editor (replacing parts of a file) | G7: It is unable to indent properly (IndentationError) | H7: Yes, it keeps "replacing" the line ' def do_generate_income_report(self, arg):' in /finance_tracker/cli.py with the same value, not knowing that the actual problem is that 'def __init__(self):' has no proper body. | I7: --- a/finance_tracker/cli.py +++ b/finance_tracker/cli.py @@ -4,6 +4,7 @@ from finance_tracker.expenses import ExpenseTracker from finance_tracker.budgets import BudgetManager from finance_tracker.users import UserManager from finance_tracker.reports import FinancialReport +from finance_tracker.income import IncomeTracker from datetime import datetime class FinanceTrackerCLI(cmd.Cmd): (str_replace_editor str_replace /finance_tracker/finance_tracker/cli.py --old_str 'from finance_tracker.reports import FinancialReport' --new_str 'from finance_tracker.reports import FinancialReport) | J7: cli.py, README.md | K7: Traceback (most recent call last): File "/finance_tracker/finance_tracker/tests/test_income.py", line 5, in <module> from finance_tracker.reports import FinancialReport File "/finance_tracker/finance_tracker/reports.py", line 5, in <module> import pandas as pd ModuleNotFoundError: No module named 'pandas' it then proceeds to installing pandas using 'pip install pandas' | L7: pandas, matplotlib | M7: Traceback (most recent call last): File "/finance_tracker/finance_tracker/tests/test_income.py", line 7, in <module> from finance_tracker.cli import FinanceTrackerCLI File "/finance_tracker/finance_tracker/cli.py", line 41 def do_generate_income_report(self, arg): ^ IndentationError: expected an indented block after function definition on line 40 | N7: cli.py | O7: str_replace_editor str_replace /finance_tracker/finance_tracker/cli.py --old_str ' def do_generate_income_report(self, arg):' --new_str ' def do_generate_income_report(self, arg): """Generate an income report: generate_income_report [start_date] [end_date]""" if not self.current_user: print("Please login first") return args = arg.split() start_date = args[0] if len(args) > 0 else None end_date = args[1] if len(args) > 1 else None try: report_data = self.income_tracker.generate_income_summary(start_date, end_date) print(json.dumps(report_data, indent=2)) except Exception as e: print(f"Error: {e}") ' It does this repeatedly without changing anything, re-runs the test and repeats. | P7: The agent does the same changes five times, sometimes running the test in between and sometimes not | Q7: 6 | R7: 5 | S7: 2 | T7: 6 | U7: 5
A8: 536e | B8: 0.017361111 | C8: income tracking feature as detailed in the PR description for the finance tracker project | D8: Yes, the task was completed successfully. | E8: execute bash commands, tool call, file reading, update function | F8: tool call | G8: IndentationError, indicating a syntax error | H8: Yes, he wanted to create a IncomeTracker class with different descriptions | I8: replace a string in the File, altering the import statement for FinancialReport and adding IncomeTracker | J8: report.py | Q8: 4 | R8: 4 | S8: 3 | T8: 4 | U8: 2
A9: 67c3 | B9: 0.017361111 | D9: No, the task was not completed. | E9: Execute solutions and take over corrections | F9: Ask and add error fixes | G9: Missing libraries, non-working feature | N9: financetracher/cli.py | O9: I think so | Q9: 3 | R9: 6 | S9: 6 | T9: 5 | U9: 4
A10: bdb6 | B10: 0.011805556 | C10: It's a helpful assistant that can interact with a computer to solve tasks. | D10: No, the task was not completed. | E10: ls, cat, str_replace_editor, python3 | F10: cat | G10: IndentationError: expected an indented block after function definition on line 40 | H10: The agent calls ls /finance_tracker/finance_tracker three times in succession, resulting in WARNING | I10: str_replace_editor str_replace /finance_tracker/finance_tracker/cli.py --old_str 'from finance_tracker.reports import FinancialReport' --new_str 'from finance_tracker.reports import FinancialReport | J10: /finance_tracker/finance_tracker/cli.py | K10: OBSERVATION: Traceback (most recent call last): File "/finance_tracker/finance_tracker/tests/test_income.py", line 5, in <module> from finance_tracker.reports import FinancialReport File "/finance_tracker/finance_tracker/reports.py", line 5, in <module> import pandas as pd ModuleNotFoundError: No module named 'pandas' pip install pandas | L10: pandas, matplotlib, | M10: OBSERVATION: Traceback (most recent call last): File "/finance_tracker/finance_tracker/tests/test_income.py", line 7, in <module> from finance_tracker.cli import FinanceTrackerCLI File "/finance_tracker/finance_tracker/cli.py", line 41 def do_generate_income_report(self, arg): ^ IndentationError: expected an indented block after function definition on line 40 | N10: /finance_tracker/finance_tracker/cli.py | O10: str_replace_editor str_replace /finance_tracker/finance_tracker/cli.py --old_str ' def do_generate_income_report(self, arg):' --new_str ' def do_generate_income_report(self, arg): """Generate an income report: generate_income_report [start_date] [end_date]""" if not self.current_user: print("Please login first") return args = arg.split() start_date = args[0] if len(args) > 0 else None end_date = args[1] if len(args) > 1 else None try: report_data = self.income_tracker.generate_income_summary(start_date, end_date) print(json.dumps(report_data, indent=2)) except Exception as e: print(f"Error: {e}") ' | P10: They are the exact same change | Q10: 3 | R10: 2 | S10: 6 | T10: 4 | U10: 2
A11: bdf7 | B11: 0.017361111 | C11: The agent's goal is to implement an finance tracker application by creating and testing the required functionalities. | D11: No, the task was not completed. | E11: Read content, Implement code, Test code, and fix code | F11: Fix code | G11: The agent has trouble implementing a correct version of the income tracker | H11: Create the `IncomeTracker` class in `income.py` and update related files in the `finance_tracker` directory to incorporate income tracking features as outlined in the PR description. | I11: The file /finance_tracker/finance_tracker/cli.py has been edited. Here's the result of running `cat -n` on a snippet of /finance_tracker/finance_tracker/cli.py: The file /finance_tracker/finance_tracker/reports.py has been edited. Here's the result of running `cat -n` on a snippet of /finance_tracker/finance_tracker/reports.py: 1 import cmd 32 "period": f"{start_date or 'all'} to {end_date or 'all'}", 2 import argparse 33 "category_totals": categories, 3 from finance_tracker.expenses import ExpenseTracker 34 "total": sum(categories.values()) 4 from finance_tracker.budgets import BudgetManager 35 } 5 from finance_tracker.users import UserManager 36 6 from finance_tracker.reports import FinancialReport 37 def generate_income_summary(self, start_date: str = None, end_date: str = None) -> Dict: 7 from finance_tracker.income import IncomeTracker 38 """Generate a summary of income by category.""" 8 from datetime import datetime 39 incomes = self.income_tracker.incomes 9 40 if start_date and end_date: 10 class FinanceTrackerCLI(cmd.Cmd): 41 incomes = [inc for inc in incomes if start_date <= inc.date <= end_date] 42 categories = {} 43 for inc in incomes: 44 cat = inc.category 45 categories[cat] = categories.get(cat, 0.0) + inc.amount 46 return { 47 "user_id": self.user_id, 48 "period": f"{start_date or 'all'} to {end_date or 'all'}", 49 "category_totals": categories, 50 "total": sum(categories.values()) 51 } 52 53 def generate_budget_comparison(self, period: str = "monthly") -> List[Dict]: 54 """Compare spending against budgets.""" 55 budgets = self.budget_manager.get_all_budgets() 56 comparison = [] Review the changes and make sure they are as expected. Edit the file again if necessary. Review the changes and make sure they are as expected. Edit the file again if necessary. | J11: cli.py | K11: IndentationError | L11: matplotlib | Q11: 5 | R11: 6 | S11: 3 | T11: 3 | U11: 5
A12: e43c | B12: 0.015625 | C12: The agent goal is to implement necessary changes following the requirements in a pull requests. It will need to first analyses this task step by step and provide candidate solutions. Then, they need to run tools to validate the correctness of candidates solutions. Finally, they will submit the solutions if they pass the validation. | D12: No, the task was not completed. | E12: run tools, generate solutions, fix solutions, submit solutions | F12: run tools | G12: The agent has trouble on generating compilable code. Some errors include "ModuleNotFoundError", indicating they fail to setup environment correctly, and "IndentationError", indicating they fails to generate syntactically correct code. | H12: Yes, the agent run programs, found some face indentation errors and then fixing these errors 4 times in a row before stopping. | I12: +from finance_tracker.income import IncomeTracker | J12: /finance_tracker/finance_tracker/cli.py | K12: The agent get a feedback that a dependency, i.e., pandas, was missing. "ModuleNotFoundError: No module named 'pandas'" Based on this feedback the agent installed this module in next action. | L12: pandas, matplotlib | M12: Traceback (most recent call last): File "/finance_tracker/finance_tracker/tests/test_income.py", line 7, in <module> from finance_tracker.cli import FinanceTrackerCLI File "/finance_tracker/finance_tracker/cli.py", line 41 def do_generate_income_report(self, arg): ^ IndentationError: expected an indented block after function definition on line 40 | N12: /finance_tracker/finance_tracker/cli.py | O12: Yes "Found submission: diff --git a/finance_tracker/cli.py b/finance_tracker/cli.py" | P12: They tried to fix same error and return same fix for all turns. | Q12: 7 | R12: 5 | S12: 3 | T12: 5 | U12: 7
A13: fe6c | B13: 0.017361111 | C13: The goal is to enhance the `finance_tracker` project by adding income tracking functionality to complement the existing expense, budget, user, and reporting features. | D13: No, the task was not completed. | E13: Gather relevant information', 'summarize requirements', 'code implementation and show the diff', 'run tests and solve runtime errors' | F13: run tests and modify the code to solve errors. | H13: Yes, maybe the step where it try to solve the same runtime errors again and again. | I13: --old_str 'from finance_tracker.reports import FinancialReport' --new_str 'from finance_tracker.reports import FinancialReport from finance_tracker.income import IncomeTracker' | J13: finance_tracker/cli.py, finance_tracker/reports.py | K13: ModuleNotFoundError: No module named 'pandas'. The agent installs the package, and allows the execution go with no reference errors. | L13: pandas | M13: Traceback (most recent call last): File "/finance_tracker/finance_tracker/tests/test_income.py", line 7, in <module> from finance_tracker.cli import FinanceTrackerCLI File "/finance_tracker/finance_tracker/cli.py", line 41 def do_generate_income_report(self, arg): ^ IndentationError: expected an indented block after function definition on line 40 | N13: cli.py | Q13: 6 | R13: 5 | S13: 4 | T13: 5 | U13: 3
A14: 1 | B14: 2 | C14: 3 | D14: 4 | E14: 5 | F14: 6 | G14: 7 | H14: 8 | I14: 9 | J14: 10 | K14: 11 | L14: 12 | M14: 13 | N14: 14 | O14: 15 | P14: 16
A15: Participant Key | C15: =C1 -> What is the primary goal of the agent? | D15: =D1 -> Did the agent complete its task? | E15: =E1 -> What are the main action categories performed by the agent? | F15: =F1 -> What is the most frequently performed action? | G15: =G1 -> What is the key challenge or issue the agent encounters during the task? | H15: =H1 -> Does the agent exhibit any repetitive behavior? If so, describe one example. | I15: =I1 -> What specific changes does the agent make to the cli.py file when it first modifies it? | J15: =J1 -> Which specific files does the agent modify to implement the income report generation feature? | ... P15: =P1 -> Analyze the final four changes the agent makes to the repository. How do these changes relate to each other? | Q15: Total Points (Unscaled) | R15: Total Points (Scaled) | S15: Overall % | T15: Participant Key | U15: Group | V15: Completion Time | W15: Percentile
A16: 5694 | B16: Points (Not Scaled) | C16: 3 | D16: 1 | E16: 1 | F16: 0 | G16: 0 | H16: 0 | I16: 0 | J16: 0 | K16: 1 | L16: 1 | M16: 1 | N16: 1 | O16: 0 | P16: 0 | Q16: =SUM(C16:P16) -> 9 | R16: {=SUMPRODUCT($C16:P16, VLOOKUP($C$15:P$15,$A$30:$C$43,3,FALSE))} -> 36 | S16: =R16/$D$45 -> 0.42857143 | T16: =A16 -> 5694 | U16: =VLOOKUP(T16,$A$48:$B$59,2,FALSE) -> B | V16: 0.017361111 | W16: =COUNTIF(R$16:R$27,">"&R16)/COUNTA(R$16:R$27) -> 0.66666667
A17: 0078 | C17: 2 | D17: 0 | E17: 0 | F17: 1 | G17: 1 | H17: 1 | I17: 1 | J17: 2 | K17: 2 | L17: 1 | M17: 1 | N17: 1 | O17: 0 | P17: 0 | Q17: =SUM(C17:P17) -> 13 | R17: {=SUMPRODUCT($C17:P17, VLOOKUP($C$15:P$15,$A$30:$C$43,3,FALSE))} -> 55 | S17: =R17/$D$45 -> 0.6547619 | T17: =A17 -> 0078 | U17: =VLOOKUP(T17,$A$48:$B$59,2,FALSE) -> A | V17: 0.017361111 | W17: =COUNTIF(R$16:R$27,">"&R17)/COUNTA(R$16:R$27) -> 0.5
A18: 18e7 | C18: 2 | D18: 0 | E18: 2 | F18: 1 | G18: 1 | H18: 2 | I18: 0 | J18: 1 | K18: 2 | L18: 1 | M18: 1 | N18: 1 | O18: 0 | P18: 1 | Q18: =SUM(C18:P18) -> 15 | R18: {=SUMPRODUCT($C18:P18, VLOOKUP($C$15:P$15,$A$30:$C$43,3,FALSE))} -> 58 | S18: =R18/$D$45 -> 0.69047619 | T18: =A18 -> 18e7 | U18: =VLOOKUP(T18,$A$48:$B$59,2,FALSE) -> A | V18: 0.017013889 | W18: =COUNTIF(R$16:R$27,">"&R18)/COUNTA(R$16:R$27) -> 0.33333333
A19: 1d20 | C19: 1 | D19: 1 | E19: 2 | F19: 1 | G19: 1 | H19: 1 | I19: 1 | J19: 1 | K19: 2 | L19: 1 | M19: 1 | N19: 1 | O19: 1 | P19: 1 | Q19: =SUM(C19:P19) -> 16 | R19: {=SUMPRODUCT($C19:P19, VLOOKUP($C$15:P$15,$A$30:$C$43,3,FALSE))} -> 71 | S19: =R19/$D$45 -> 0.8452381 | T19: =A19 -> 1d20 | U19: =VLOOKUP(T19,$A$48:$B$59,2,FALSE) -> A | V19: 0.017013889 | W19: =COUNTIF(R$16:R$27,">"&R19)/COUNTA(R$16:R$27) -> 0.083333333
A20: 33c6 | C20: 1 | D20: 1 | E20: 2 | F20: 1 | G20: 1 | H20: 2 | I20: 1 | J20: 1 | K20: 2 | L20: 1 | M20: 1 | N20: 1 | O20: 1 | P20: 1 | Q20: =SUM(C20:P20) -> 17 | R20: {=SUMPRODUCT($C20:P20, VLOOKUP($C$15:P$15,$A$30:$C$43,3,FALSE))} -> 74 | S20: =R20/$D$45 -> 0.88095238 | T20: =A20 -> 33c6 | U20: =VLOOKUP(T20,$A$48:$B$59,2,FALSE) -> A | V20: 0.017361111 | W20: =COUNTIF(R$16:R$27,">"&R20)/COUNTA(R$16:R$27) -> 0
A21: 49F7 | C21: 2 | D21: 1 | E21: 2 | F21: 1 | G21: 1 | H21: 2 | I21: 0 | J21: 0 | K21: 2 | L21: 1 | M21: 1 | N21: 1 | O21: 1 | P21: 1 | Q21: =SUM(C21:P21) -> 16 | R21: {=SUMPRODUCT($C21:P21, VLOOKUP($C$15:P$15,$A$30:$C$43,3,FALSE))} -> 67 | S21: =R21/$D$45 -> 0.79761905 | T21: =A21 -> 49F7 | U21: =VLOOKUP(T21,$A$48:$B$59,2,FALSE) -> B | V21: 0.016666667 | W21: =COUNTIF(R$16:R$27,">"&R21)/COUNTA(R$16:R$27) -> 0.16666667
A22: 536E | C22: 2 | D22: 0 | E22: 2 | F22: 0 | G22: 1 | H22: 0 | I22: 1 | J22: 0 | K22: 0 | L22: 0 | M22: 0 | N22: 0 | O22: 0 | P22: 0 | Q22: =SUM(C22:P22) -> 6 | R22: {=SUMPRODUCT($C22:P22, VLOOKUP($C$15:P$15,$A$30:$C$43,3,FALSE))} -> 22 | S22: =R22/$D$45 -> 0.26190476 | T22: =A22 -> 536E | U22: =VLOOKUP(T22,$A$48:$B$59,2,FALSE) -> A | V22: 0.017361111 | W22: =COUNTIF(R$16:R$27,">"&R22)/COUNTA(R$16:R$27) -> 0.75
A23: 67c3 | C23: 0 | D23: 1 | E23: 0 | F23: 0 | G23: 0 | H23: 0 | I23: 0 | J23: 0 | K23: 0 | L23: 0 | M23: 0 | N23: 1 | O23: 0 | P23: 0 | Q23: =SUM(C23:P23) -> 2 | R23: {=SUMPRODUCT($C23:P23, VLOOKUP($C$15:P$15,$A$30:$C$43,3,FALSE))} -> 12 | S23: =R23/$D$45 -> 0.14285714 | T23: =A23 -> 67c3 | U23: =VLOOKUP(T23,$A$48:$B$59,2,FALSE) -> B | V23: 0.017361111 | W23: =COUNTIF(R$16:R$27,">"&R23)/COUNTA(R$16:R$27) -> 0.91666667
A24: bdb6 | C24: 0 | D24: 1 | E24: 2 | F24: 0 | G24: 1 | H24: 2 | I24: 1 | J24: 0 | K24: 2 | L24: 1 | M24: 1 | N24: 1 | O24: 1 | P24: 1 | Q24: =SUM(C24:P24) -> 14 | R24: {=SUMPRODUCT($C24:P24, VLOOKUP($C$15:P$15,$A$30:$C$43,3,FALSE))} -> 63 | S24: =R24/$D$45 -> 0.75 | T24: =A24 -> bdb6 | U24: =VLOOKUP(T24,$A$48:$B$59,2,FALSE) -> B | V24: 0.011805556 | W24: =COUNTIF(R$16:R$27,">"&R24)/COUNTA(R$16:R$27) -> 0.25
A25: bdf7 | C25: 0 | D25: 1 | E25: 2 | F25: 1 | G25: 0 | H25: 0 | I25: 0 | J25: 0 | K25: 0 | L25: 0 | M25: 0 | N25: 0 | O25: 0 | P25: 0 | Q25: =SUM(C25:P25) -> 4 | R25: {=SUMPRODUCT($C25:P25, VLOOKUP($C$15:P$15,$A$30:$C$43,3,FALSE))} -> 18 | S25: =R25/$D$45 -> 0.21428571 | T25: =A25 -> bdf7 | U25: =VLOOKUP(T25,$A$48:$B$59,2,FALSE) -> A | V25: 0.017361111 | W25: =COUNTIF(R$16:R$27,">"&R25)/COUNTA(R$16:R$27) -> 0.83333333
A26: e43c | C26: 1 | D26: 1 | E26: 2 | F26: 0 | G26: 1 | H26: 1 | I26: 1 | J26: 0 | K26: 2 | L26: 1 | M26: 1 | N26: 1 | O26: 0 | P26: 1 | Q26: =SUM(C26:P26) -> 13 | R26: {=SUMPRODUCT($C26:P26, VLOOKUP($C$15:P$15,$A$30:$C$43,3,FALSE))} -> 56 | S26: =R26/$D$45 -> 0.66666667 | T26: =A26 -> e43c | U26: =VLOOKUP(T26,$A$48:$B$59,2,FALSE) -> B | V26: 0.015625 | W26: =COUNTIF(R$16:R$27,">"&R26)/COUNTA(R$16:R$27) -> 0.41666667
A27: fe6c | C27: 3 | D27: 1 | E27: 1 | F27: 1 | G27: 0 | H27: 1 | I27: 1 | J27: 1 | K27: 2 | L27: 0 | M27: 1 | N27: 1 | O27: 0 | P27: 0 | Q27: =SUM(C27:P27) -> 13 | R27: {=SUMPRODUCT($C27:P27, VLOOKUP($C$15:P$15,$A$30:$C$43,3,FALSE))} -> 51 | S27: =R27/$D$45 -> 0.60714286 | T27: =A27 -> fe6c | U27: =VLOOKUP(T27,$A$48:$B$59,2,FALSE) -> B | V27: 0.017361111 | W27: =COUNTIF(R$16:R$27,">"&R27)/COUNTA(R$16:R$27) -> 0.58333333
A29: Question | B29: Max Points | C29: Scale Multiplier | D29: Max Points (Scaled)
A30: =C1 -> What is the primary goal of the agent? | B30: 3 | C30: =LCM(B$30:B$43)/B30 -> 2 | D30: =B30*C30 -> 6
A31: =D1 -> Did the agent complete its task? | B31: 1 | C31: =LCM(B$30:B$43)/B31 -> 6 | D31: =B31*C31 -> 6
A32: =E1 -> What are the main action categories performed by the agent? | B32: 2 | C32: =LCM(B$30:B$43)/B32 -> 3 | D32: =B32*C32 -> 6
A33: =F1 -> What is the most frequently performed action? | B33: 1 | C33: =LCM(B$30:B$43)/B33 -> 6 | D33: =B33*C33 -> 6
A34: =G1 -> What is the key challenge or issue the agent encounters during the task? | B34: 1 | C34: =LCM(B$30:B$43)/B34 -> 6 | D34: =B34*C34 -> 6
A35: =H1 -> Does the agent exhibit any repetitive behavior? If so, describe one example. | B35: 2 | C35: =LCM(B$30:B$43)/B35 -> 3 | D35: =B35*C35 -> 6
A36: =I1 -> What specific changes does the agent make to the cli.py file when it first modifies it? | B36: 1 | C36: =LCM(B$30:B$43)/B36 -> 6 | D36: =B36*C36 -> 6
A37: =J1 -> Which specific files does the agent modify to implement the income report generation feature? | B37: 2 | C37: =LCM(B$30:B$43)/B37 -> 3 | D37: =B37*C37 -> 6
A38: =K1 -> What feedback does the agent receive after its first attempt to run the test script for the finance tracker, and how does it influence the next action? | B38: 2 | C38: =LCM(B$30:B$43)/B38 -> 3 | D38: =B38*C38 -> 6
A39: =L1 -> Which Python packages does the agent install over the course of the run? | B39: 1 | C39: =LCM(B$30:B$43)/B39 -> 6 | D39: =B39*C39 -> 6
A40: =M1 -> What feedback does the agent receive from running the test script for the finance tracker after it has solved all import issues? | B40: 1 | C40: =LCM(B$30:B$43)/B40 -> 6 | D40: =B40*C40 -> 6
A41: =N1 -> Which file is the agent primarily focused on modifying towards the end of the run? | B41: 1 | C41: =LCM(B$30:B$43)/B41 -> 6 | D41: =B41*C41 -> 6
A42: =O1 -> Does the agent ever attempt to make the same change twice before reevaluating the tests? If so, describe one instance. | B42: 1 | C42: =LCM(B$30:B$43)/B42 -> 6 | D42: =B42*C42 -> 6
A43: =P1 -> Analyze the final four changes the agent makes to the repository. How do these changes relate to each other? | B43: 2 | C43: =LCM(B$30:B$43)/B43 -> 3 | D43: =B43*C43 -> 6
A45: Total | B45: =SUM(B30:B43) -> 21 | D45: =SUM(D30:D43) -> 84
A47: Participant Key | B47: Group
A48: fe6c | B48: B
A49: 67c3 | B49: B
A50: 0078 | B50: A
A51: 1d20 | B51: A
A52: 33c6 | B52: A
A53: 49f7 | B53: B
A54: 536e | B54: A
A55: 5694 | B55: B
A56: bdb6 | B56: B
A57: bdf7 | B57: A
A58: 18e7 | B58: A
... A82: bdb6 | B82: Advanced
A83: bdf7 | B83: Basic | C83: 3 | D83: 4
A84: 18e7 | B84: Advanced
A85: e43c | B85: Moderate

Sheet Task 2
A1: Participant Key | B1: Completion Time | C1: Find and describe all potential bugs! | D1: Mental Demand | E1: Temporal Demand | F1: Performance | G1: Effort | H1: Frustration | J1: Grade
A2: 5694 | B2: 0.0083333333 | C2: it proposes the same fix over and over again. | D2: 5 | E2: 7 | F2: 6 | G2: 5 | H2: 7 | J2: 0
A3: 0078 | B3: 0.0083333333 | C3: The LLM suggests to update the read method to account for both \r and \n characters, but the agent misinterprets it and removes the \n (which was correct), instead of adding a new if-case for \r. | D3: 3 | E3: 2 | F3: 4 | G3: 3 | H3: 2 | J3: 0
A4: 1d20 | B4: 0.0083333333 | C4: It seems that the tool implementation is buggy and when the agent tries to modify the file, the process does not work correctly. From my inspections the agent tries to modify something, but the resulting file contents are not as expected. | D4: 6 | E4: 7 | F4: 2 | G4: 6 | H4: 1 | J4: 1
A5: 33c6 | B5: 0.00625 | C5: The LLM calls the write_fix tool with a meaningful fix trying to modify the line 58 to also handle other line endings. There seems to however be a bug in the implementation of applying the proposed fix to the repository. The file is not correctly modified but the line to modify is only removed. | D5: 4 | E5: 2 | F5: 2 | G5: 2 | H5: 1 | J5: 1
A6: 49f7 | B6: 0.0083333333 | C6: Test 'org.apache.commons.csv.CSVParserTest::testGetLineNumberWithCR' fails. However, the agent only is shown code from code from 'org.apache.commons.csv.CSVParserTest::testGetLineNumberWithCRLF' | D6: 7 | E6: 6 | F6: 5 | G6: 6 | H6: 7 | J6: 0
A7: 536e | B7: 0.0083333333 | C7: The fix description from the agent isnt good enough for the LLM. | D7: 6 | E7: 6 | F7: 2 | G7: 6 | H7: 5 | J7: 0
A8: 67c3 | B8: 0.0083333333 | D8: 5 | E8: 7 | F8: 7 | G8: 6 | H8: 7 | J8: 0
A9: bdb6 | B9: 0.0065972222 | C9: I do not see an fatal bug but continued warning of repetition detected! with repeated write_fix seems concerning. The core should give more drastic guidance or the warning is not effective. | D9: 6 | E9: 5 | F9: 3 | G9: 4 | H9: 3 | J9: 0
A10: bdf7 | B10: 0.00625 | C10: The agent calls the write_fix tool to fix the problem but nothing is changed | D10: 3 | E10: 3 | F10: 4 | G10: 3 | H10: 2 | J10: 1
A11: e43c | B11: 0.00625 | C11: The write_fix() tool should generate the patch and apply this patch to current repository by modifying the read() method. However, I guess it only generate the fix and do not apply into current repository. That is reason why the test results are always failures. | D11: 7 | E11: 7 | F11: 4 | G11: 7 | H11: 6 | J11: 1
A12: fe6c | B12: 0.0083333333 | C12: Agent's logic: failed to change to another method to fix the issue. Implementation: the line break conditional statements seems was incorrect at some point. | D12: 6 | E12: 5 | F12: 3 | G12: 4 | H12: 4 | J12: 0

Sheet Task 3
A1: Participant Key | B1: Completion Time | C1: Find and describe all potential bugs! | D1: Mental Demand | E1: Temporal Demand | F1: Performance | G1: Effort | H1: Frustration | J1: Grade
A2: 5694 | B2: 0.0083333333 | C2: Problem: it seems that the files which should be read have invalid syntax. The Agent is does not seem to be able to fix it... Potential Bug: The Bug seems to be related with java, maybe the installation failed, or java is not yet a environment variable. | D2: 5 | E2: 6 | F2: 6 | G2: 6 | H2: 6 | J2: 0
A3: 0078 | B3: 0.0083333333 | C3: The agent tries to use forbidden commands (for which it has no permission) multiple times. It also tries to chain commands, which also does not seem to work. The LLM suggests to write a dockerfile, but the agent runs into problems. The agent and LLM do not seem to recognize that they are running in circles. It seems like after "The agent acknowledges that the LLM's training data is current only until October 2023.", the agent loses its "history" and tries commands again which have not worked before. | D3: 4 | E3: 3 | F3: 5 | G3: 4 | H3: 4 | J3: 1
A4: 1d20 | B4: 0.0048611111 | C4: The main issue is that the agent was never able to create a working dockerfile to try different approaches to resolve the problem. The main problem I see in this trajectory is that the error message from one write to a dockerfile was not returned to the agent. The other logic problem that could exist is that the agent seems to not have a good instruction on that it has to first create a dockerfile to be able to run all bash commands. | D4: 4 | E4: 2 | F4: 1 | G4: 2 | H4: 1 | J4: 1
A5: 33c6 | B5: 0.0083333333 | C5: At the beginning the LLM tries to run a bash command to setup openjdk eventhough it is not allowed to do this at that state. In the second tool call it tries to run an unallowed command. The third LLM response is empty as the LLM rejects the prompt. Similar problems occur multiple times. The agent continues to fail to create a script for seting up the docker environment. After a while the LLM is able to successfully call the tool to write a docker file, but the agent fails to start the docker image. It tries this multiple more times but it is not clear why it fails. | D5: 5 | E5: 5 | F5: 3 | G5: 5 | H5: 2 | J5: 1
A6: 49F7 | B6: 0.0083333333 | C6: Docker commands are not allowed on the system. The agent is told upfront that this is not possible, but it does it anyways. At first, it correctly uses write_to_file instead, but when the docker container fails to start for an unspecified reason, the agent tries to "escape" into a new shell that does not have this restriction or issues with the docker command. That is prohibited as well. ... | D6: 7 | E6: 7 | F6: 5 | G6: 6 | H6: 5 | J6: 1
A7: 536E | B7: 0.0083333333 | C7: The command line could not handle the agents input. It repeats it self. | D7: 6 | E7: 6 | F7: 2 | G7: 6 | H7: 6 | J7: 0
A8: 67c3 | B8: 0.0083333333 | C8: No access to the environment and therefore can’t install or update anything, missing tools that are supposed to be used | D8: 5 | E8: 7 | F8: 4 | G8: 6 | H8: 5 | J8: 0
A9: bdb6 | B9: 0.0069444444 | C9: I don't see any obvious problem with agent's logic. | D9: 6 | E9: 5 | F9: 3 | G9: 5 | H9: 4 | J9: 0
A10: bdf7 | B10: 0.0034722222 | C10: The agent executes commands that are not available or allowed | D10: 2 | E10: 2 | F10: 4 | G10: 3 | H10: 2 | J10: 0
A11: e43c | B11: 0.0048611111 | C11: I think the error lies on tool design to execute command. This based on the observation that this error message "SYSTEM: Unable to execute command" repeat 39 times in the logs. Without executing the command, the agent cannot define the next steps, leading to failures. | D11: 5 | E11: 4 | F11: 1 | G11: 5 | H11: 3 | J11: 0
A12: fe6c | B12: 0.0083333333 | C12: Agent's decision making: the failed command outputs mention that more commands could be run in a docker container, but the agent fails to adjust the next steps to adapt it. Logic: allows the failed steps repeat multiple times. | D12: 6 | E12: 5 | F12: 5 | G12: 5 | H12: 4 | J12: 0
